{
  "type": "File",
  "start": 0,
  "end": 2624,
  "loc": {
    "start": {
      "line": 1,
      "column": 0
    },
    "end": {
      "line": 87,
      "column": 0
    }
  },
  "program": {
    "type": "Program",
    "start": 0,
    "end": 2624,
    "loc": {
      "start": {
        "line": 1,
        "column": 0
      },
      "end": {
        "line": 87,
        "column": 0
      }
    },
    "sourceType": "module",
    "body": [
      {
        "type": "ImportDeclaration",
        "start": 14,
        "end": 53,
        "loc": {
          "start": {
            "line": 3,
            "column": 0
          },
          "end": {
            "line": 3,
            "column": 39
          }
        },
        "specifiers": [
          {
            "type": "ImportDefaultSpecifier",
            "start": 21,
            "end": 32,
            "loc": {
              "start": {
                "line": 3,
                "column": 7
              },
              "end": {
                "line": 3,
                "column": 18
              }
            },
            "local": {
              "type": "Identifier",
              "start": 21,
              "end": 32,
              "loc": {
                "start": {
                  "line": 3,
                  "column": 7
                },
                "end": {
                  "line": 3,
                  "column": 18
                },
                "identifierName": "SCNGeometry"
              },
              "name": "SCNGeometry"
            }
          }
        ],
        "source": {
          "type": "StringLiteral",
          "start": 38,
          "end": 53,
          "loc": {
            "start": {
              "line": 3,
              "column": 24
            },
            "end": {
              "line": 3,
              "column": 39
            }
          },
          "extra": {
            "rawValue": "./SCNGeometry",
            "raw": "'./SCNGeometry'"
          },
          "value": "./SCNGeometry",
          "leadingComments": null,
          "trailingComments": null
        },
        "trailingComments": [
          {
            "type": "CommentBlock",
            "value": "*\n * A rectangular, one-sided plane geometry of specified width and height.\n * @access public\n * @extends {SCNGeometry}\n * @see https://developer.apple.com/reference/scenekit/scnplane\n ",
            "start": 56,
            "end": 245,
            "loc": {
              "start": {
                "line": 6,
                "column": 0
              },
              "end": {
                "line": 11,
                "column": 3
              }
            }
          }
        ]
      },
      {
        "type": "ExportDefaultDeclaration",
        "start": 246,
        "end": 2623,
        "loc": {
          "start": {
            "line": 12,
            "column": 0
          },
          "end": {
            "line": 86,
            "column": 1
          }
        },
        "declaration": {
          "type": "ClassDeclaration",
          "start": 261,
          "end": 2623,
          "loc": {
            "start": {
              "line": 12,
              "column": 15
            },
            "end": {
              "line": 86,
              "column": 1
            }
          },
          "id": {
            "type": "Identifier",
            "start": 267,
            "end": 275,
            "loc": {
              "start": {
                "line": 12,
                "column": 21
              },
              "end": {
                "line": 12,
                "column": 29
              },
              "identifierName": "SCNPlane"
            },
            "name": "SCNPlane",
            "leadingComments": null
          },
          "superClass": {
            "type": "Identifier",
            "start": 284,
            "end": 295,
            "loc": {
              "start": {
                "line": 12,
                "column": 38
              },
              "end": {
                "line": 12,
                "column": 49
              },
              "identifierName": "SCNGeometry"
            },
            "name": "SCNGeometry"
          },
          "body": {
            "type": "ClassBody",
            "start": 296,
            "end": 2623,
            "loc": {
              "start": {
                "line": 12,
                "column": 50
              },
              "end": {
                "line": 86,
                "column": 1
              }
            },
            "body": [
              {
                "type": "ClassMethod",
                "start": 371,
                "end": 1915,
                "loc": {
                  "start": {
                    "line": 19,
                    "column": 2
                  },
                  "end": {
                    "line": 71,
                    "column": 3
                  }
                },
                "computed": false,
                "key": {
                  "type": "Identifier",
                  "start": 371,
                  "end": 375,
                  "loc": {
                    "start": {
                      "line": 19,
                      "column": 2
                    },
                    "end": {
                      "line": 19,
                      "column": 6
                    },
                    "identifierName": "init"
                  },
                  "name": "init",
                  "leadingComments": null
                },
                "static": false,
                "kind": "method",
                "id": null,
                "generator": false,
                "expression": false,
                "async": false,
                "params": [],
                "body": {
                  "type": "BlockStatement",
                  "start": 378,
                  "end": 1915,
                  "loc": {
                    "start": {
                      "line": 19,
                      "column": 9
                    },
                    "end": {
                      "line": 71,
                      "column": 3
                    }
                  },
                  "body": [
                    {
                      "type": "ExpressionStatement",
                      "start": 614,
                      "end": 628,
                      "loc": {
                        "start": {
                          "line": 28,
                          "column": 4
                        },
                        "end": {
                          "line": 28,
                          "column": 18
                        }
                      },
                      "expression": {
                        "type": "AssignmentExpression",
                        "start": 614,
                        "end": 628,
                        "loc": {
                          "start": {
                            "line": 28,
                            "column": 4
                          },
                          "end": {
                            "line": 28,
                            "column": 18
                          }
                        },
                        "operator": "=",
                        "left": {
                          "type": "MemberExpression",
                          "start": 614,
                          "end": 624,
                          "loc": {
                            "start": {
                              "line": 28,
                              "column": 4
                            },
                            "end": {
                              "line": 28,
                              "column": 14
                            }
                          },
                          "object": {
                            "type": "ThisExpression",
                            "start": 614,
                            "end": 618,
                            "loc": {
                              "start": {
                                "line": 28,
                                "column": 4
                              },
                              "end": {
                                "line": 28,
                                "column": 8
                              }
                            },
                            "leadingComments": null
                          },
                          "property": {
                            "type": "Identifier",
                            "start": 619,
                            "end": 624,
                            "loc": {
                              "start": {
                                "line": 28,
                                "column": 9
                              },
                              "end": {
                                "line": 28,
                                "column": 14
                              },
                              "identifierName": "width"
                            },
                            "name": "width"
                          },
                          "computed": false,
                          "leadingComments": null
                        },
                        "right": {
                          "type": "NumericLiteral",
                          "start": 627,
                          "end": 628,
                          "loc": {
                            "start": {
                              "line": 28,
                              "column": 17
                            },
                            "end": {
                              "line": 28,
                              "column": 18
                            }
                          },
                          "extra": {
                            "rawValue": 0,
                            "raw": "0"
                          },
                          "value": 0,
                          "leadingComments": null,
                          "trailingComments": null
                        },
                        "leadingComments": null,
                        "trailingComments": null
                      },
                      "leadingComments": [
                        {
                          "type": "CommentLine",
                          "value": " Adjusting a Plane’s Dimensions",
                          "start": 385,
                          "end": 418,
                          "loc": {
                            "start": {
                              "line": 21,
                              "column": 4
                            },
                            "end": {
                              "line": 21,
                              "column": 37
                            }
                          }
                        },
                        {
                          "type": "CommentBlock",
                          "value": "*\n     * The extent of the plane along its horizontal axis. Animatable.\n     * @type {number}\n     * @see https://developer.apple.com/reference/scenekit/scnplane/1523782-width\n     ",
                          "start": 424,
                          "end": 609,
                          "loc": {
                            "start": {
                              "line": 23,
                              "column": 4
                            },
                            "end": {
                              "line": 27,
                              "column": 7
                            }
                          }
                        }
                      ],
                      "trailingComments": [
                        {
                          "type": "CommentBlock",
                          "value": "*\n     * The extent of the plane along its vertical axis. Animatable.\n     * @type {number}\n     * @see https://developer.apple.com/reference/scenekit/scnplane/1522837-height\n     ",
                          "start": 634,
                          "end": 818,
                          "loc": {
                            "start": {
                              "line": 30,
                              "column": 4
                            },
                            "end": {
                              "line": 34,
                              "column": 7
                            }
                          }
                        }
                      ]
                    },
                    {
                      "type": "ExpressionStatement",
                      "start": 823,
                      "end": 838,
                      "loc": {
                        "start": {
                          "line": 35,
                          "column": 4
                        },
                        "end": {
                          "line": 35,
                          "column": 19
                        }
                      },
                      "expression": {
                        "type": "AssignmentExpression",
                        "start": 823,
                        "end": 838,
                        "loc": {
                          "start": {
                            "line": 35,
                            "column": 4
                          },
                          "end": {
                            "line": 35,
                            "column": 19
                          }
                        },
                        "operator": "=",
                        "left": {
                          "type": "MemberExpression",
                          "start": 823,
                          "end": 834,
                          "loc": {
                            "start": {
                              "line": 35,
                              "column": 4
                            },
                            "end": {
                              "line": 35,
                              "column": 15
                            }
                          },
                          "object": {
                            "type": "ThisExpression",
                            "start": 823,
                            "end": 827,
                            "loc": {
                              "start": {
                                "line": 35,
                                "column": 4
                              },
                              "end": {
                                "line": 35,
                                "column": 8
                              }
                            },
                            "leadingComments": null
                          },
                          "property": {
                            "type": "Identifier",
                            "start": 828,
                            "end": 834,
                            "loc": {
                              "start": {
                                "line": 35,
                                "column": 9
                              },
                              "end": {
                                "line": 35,
                                "column": 15
                              },
                              "identifierName": "height"
                            },
                            "name": "height"
                          },
                          "computed": false,
                          "leadingComments": null
                        },
                        "right": {
                          "type": "NumericLiteral",
                          "start": 837,
                          "end": 838,
                          "loc": {
                            "start": {
                              "line": 35,
                              "column": 18
                            },
                            "end": {
                              "line": 35,
                              "column": 19
                            }
                          },
                          "extra": {
                            "rawValue": 0,
                            "raw": "0"
                          },
                          "value": 0,
                          "leadingComments": null,
                          "trailingComments": null
                        },
                        "leadingComments": null,
                        "trailingComments": null
                      },
                      "leadingComments": [
                        {
                          "type": "CommentBlock",
                          "value": "*\n     * The extent of the plane along its vertical axis. Animatable.\n     * @type {number}\n     * @see https://developer.apple.com/reference/scenekit/scnplane/1522837-height\n     ",
                          "start": 634,
                          "end": 818,
                          "loc": {
                            "start": {
                              "line": 30,
                              "column": 4
                            },
                            "end": {
                              "line": 34,
                              "column": 7
                            }
                          }
                        }
                      ],
                      "trailingComments": [
                        {
                          "type": "CommentLine",
                          "value": " Adjusting Geometric Detail",
                          "start": 845,
                          "end": 874,
                          "loc": {
                            "start": {
                              "line": 38,
                              "column": 4
                            },
                            "end": {
                              "line": 38,
                              "column": 33
                            }
                          }
                        },
                        {
                          "type": "CommentBlock",
                          "value": "*\n     * The number of subdivisions in the plane’s surface along its horizontal axis. Animatable.\n     * @type {number}\n     * @see https://developer.apple.com/reference/scenekit/scnplane/1523991-widthsegmentcount\n     ",
                          "start": 880,
                          "end": 1103,
                          "loc": {
                            "start": {
                              "line": 40,
                              "column": 4
                            },
                            "end": {
                              "line": 44,
                              "column": 7
                            }
                          }
                        }
                      ]
                    },
                    {
                      "type": "ExpressionStatement",
                      "start": 1108,
                      "end": 1134,
                      "loc": {
                        "start": {
                          "line": 45,
                          "column": 4
                        },
                        "end": {
                          "line": 45,
                          "column": 30
                        }
                      },
                      "expression": {
                        "type": "AssignmentExpression",
                        "start": 1108,
                        "end": 1134,
                        "loc": {
                          "start": {
                            "line": 45,
                            "column": 4
                          },
                          "end": {
                            "line": 45,
                            "column": 30
                          }
                        },
                        "operator": "=",
                        "left": {
                          "type": "MemberExpression",
                          "start": 1108,
                          "end": 1130,
                          "loc": {
                            "start": {
                              "line": 45,
                              "column": 4
                            },
                            "end": {
                              "line": 45,
                              "column": 26
                            }
                          },
                          "object": {
                            "type": "ThisExpression",
                            "start": 1108,
                            "end": 1112,
                            "loc": {
                              "start": {
                                "line": 45,
                                "column": 4
                              },
                              "end": {
                                "line": 45,
                                "column": 8
                              }
                            },
                            "leadingComments": null
                          },
                          "property": {
                            "type": "Identifier",
                            "start": 1113,
                            "end": 1130,
                            "loc": {
                              "start": {
                                "line": 45,
                                "column": 9
                              },
                              "end": {
                                "line": 45,
                                "column": 26
                              },
                              "identifierName": "widthSegmentCount"
                            },
                            "name": "widthSegmentCount"
                          },
                          "computed": false,
                          "leadingComments": null
                        },
                        "right": {
                          "type": "NumericLiteral",
                          "start": 1133,
                          "end": 1134,
                          "loc": {
                            "start": {
                              "line": 45,
                              "column": 29
                            },
                            "end": {
                              "line": 45,
                              "column": 30
                            }
                          },
                          "extra": {
                            "rawValue": 0,
                            "raw": "0"
                          },
                          "value": 0,
                          "leadingComments": null,
                          "trailingComments": null
                        },
                        "leadingComments": null,
                        "trailingComments": null
                      },
                      "leadingComments": [
                        {
                          "type": "CommentLine",
                          "value": " Adjusting Geometric Detail",
                          "start": 845,
                          "end": 874,
                          "loc": {
                            "start": {
                              "line": 38,
                              "column": 4
                            },
                            "end": {
                              "line": 38,
                              "column": 33
                            }
                          }
                        },
                        {
                          "type": "CommentBlock",
                          "value": "*\n     * The number of subdivisions in the plane’s surface along its horizontal axis. Animatable.\n     * @type {number}\n     * @see https://developer.apple.com/reference/scenekit/scnplane/1523991-widthsegmentcount\n     ",
                          "start": 880,
                          "end": 1103,
                          "loc": {
                            "start": {
                              "line": 40,
                              "column": 4
                            },
                            "end": {
                              "line": 44,
                              "column": 7
                            }
                          }
                        }
                      ],
                      "trailingComments": [
                        {
                          "type": "CommentBlock",
                          "value": "*\n     * The number of subdivisions in the plane’s surface along its vertical axis. Animatable.\n     * @type {number}\n     * @see https://developer.apple.com/reference/scenekit/scnplane/1522889-heightsegmentcount\n     ",
                          "start": 1140,
                          "end": 1362,
                          "loc": {
                            "start": {
                              "line": 47,
                              "column": 4
                            },
                            "end": {
                              "line": 51,
                              "column": 7
                            }
                          }
                        }
                      ]
                    },
                    {
                      "type": "ExpressionStatement",
                      "start": 1367,
                      "end": 1394,
                      "loc": {
                        "start": {
                          "line": 52,
                          "column": 4
                        },
                        "end": {
                          "line": 52,
                          "column": 31
                        }
                      },
                      "expression": {
                        "type": "AssignmentExpression",
                        "start": 1367,
                        "end": 1394,
                        "loc": {
                          "start": {
                            "line": 52,
                            "column": 4
                          },
                          "end": {
                            "line": 52,
                            "column": 31
                          }
                        },
                        "operator": "=",
                        "left": {
                          "type": "MemberExpression",
                          "start": 1367,
                          "end": 1390,
                          "loc": {
                            "start": {
                              "line": 52,
                              "column": 4
                            },
                            "end": {
                              "line": 52,
                              "column": 27
                            }
                          },
                          "object": {
                            "type": "ThisExpression",
                            "start": 1367,
                            "end": 1371,
                            "loc": {
                              "start": {
                                "line": 52,
                                "column": 4
                              },
                              "end": {
                                "line": 52,
                                "column": 8
                              }
                            },
                            "leadingComments": null
                          },
                          "property": {
                            "type": "Identifier",
                            "start": 1372,
                            "end": 1390,
                            "loc": {
                              "start": {
                                "line": 52,
                                "column": 9
                              },
                              "end": {
                                "line": 52,
                                "column": 27
                              },
                              "identifierName": "heightSegmentCount"
                            },
                            "name": "heightSegmentCount"
                          },
                          "computed": false,
                          "leadingComments": null
                        },
                        "right": {
                          "type": "NumericLiteral",
                          "start": 1393,
                          "end": 1394,
                          "loc": {
                            "start": {
                              "line": 52,
                              "column": 30
                            },
                            "end": {
                              "line": 52,
                              "column": 31
                            }
                          },
                          "extra": {
                            "rawValue": 0,
                            "raw": "0"
                          },
                          "value": 0,
                          "leadingComments": null,
                          "trailingComments": null
                        },
                        "leadingComments": null,
                        "trailingComments": null
                      },
                      "leadingComments": [
                        {
                          "type": "CommentBlock",
                          "value": "*\n     * The number of subdivisions in the plane’s surface along its vertical axis. Animatable.\n     * @type {number}\n     * @see https://developer.apple.com/reference/scenekit/scnplane/1522889-heightsegmentcount\n     ",
                          "start": 1140,
                          "end": 1362,
                          "loc": {
                            "start": {
                              "line": 47,
                              "column": 4
                            },
                            "end": {
                              "line": 51,
                              "column": 7
                            }
                          }
                        }
                      ],
                      "trailingComments": [
                        {
                          "type": "CommentLine",
                          "value": " Adding Rounded Corners",
                          "start": 1401,
                          "end": 1426,
                          "loc": {
                            "start": {
                              "line": 55,
                              "column": 4
                            },
                            "end": {
                              "line": 55,
                              "column": 29
                            }
                          }
                        },
                        {
                          "type": "CommentBlock",
                          "value": "*\n     * The radius of curvature for the plane’s corners. Animatable.\n     * @type {number}\n     * @see https://developer.apple.com/reference/scenekit/scnplane/1523005-cornerradius\n     ",
                          "start": 1432,
                          "end": 1622,
                          "loc": {
                            "start": {
                              "line": 57,
                              "column": 4
                            },
                            "end": {
                              "line": 61,
                              "column": 7
                            }
                          }
                        }
                      ]
                    },
                    {
                      "type": "ExpressionStatement",
                      "start": 1627,
                      "end": 1648,
                      "loc": {
                        "start": {
                          "line": 62,
                          "column": 4
                        },
                        "end": {
                          "line": 62,
                          "column": 25
                        }
                      },
                      "expression": {
                        "type": "AssignmentExpression",
                        "start": 1627,
                        "end": 1648,
                        "loc": {
                          "start": {
                            "line": 62,
                            "column": 4
                          },
                          "end": {
                            "line": 62,
                            "column": 25
                          }
                        },
                        "operator": "=",
                        "left": {
                          "type": "MemberExpression",
                          "start": 1627,
                          "end": 1644,
                          "loc": {
                            "start": {
                              "line": 62,
                              "column": 4
                            },
                            "end": {
                              "line": 62,
                              "column": 21
                            }
                          },
                          "object": {
                            "type": "ThisExpression",
                            "start": 1627,
                            "end": 1631,
                            "loc": {
                              "start": {
                                "line": 62,
                                "column": 4
                              },
                              "end": {
                                "line": 62,
                                "column": 8
                              }
                            },
                            "leadingComments": null
                          },
                          "property": {
                            "type": "Identifier",
                            "start": 1632,
                            "end": 1644,
                            "loc": {
                              "start": {
                                "line": 62,
                                "column": 9
                              },
                              "end": {
                                "line": 62,
                                "column": 21
                              },
                              "identifierName": "cornerRadius"
                            },
                            "name": "cornerRadius"
                          },
                          "computed": false,
                          "leadingComments": null
                        },
                        "right": {
                          "type": "NumericLiteral",
                          "start": 1647,
                          "end": 1648,
                          "loc": {
                            "start": {
                              "line": 62,
                              "column": 24
                            },
                            "end": {
                              "line": 62,
                              "column": 25
                            }
                          },
                          "extra": {
                            "rawValue": 0,
                            "raw": "0"
                          },
                          "value": 0,
                          "leadingComments": null,
                          "trailingComments": null
                        },
                        "leadingComments": null,
                        "trailingComments": null
                      },
                      "leadingComments": [
                        {
                          "type": "CommentLine",
                          "value": " Adding Rounded Corners",
                          "start": 1401,
                          "end": 1426,
                          "loc": {
                            "start": {
                              "line": 55,
                              "column": 4
                            },
                            "end": {
                              "line": 55,
                              "column": 29
                            }
                          }
                        },
                        {
                          "type": "CommentBlock",
                          "value": "*\n     * The radius of curvature for the plane’s corners. Animatable.\n     * @type {number}\n     * @see https://developer.apple.com/reference/scenekit/scnplane/1523005-cornerradius\n     ",
                          "start": 1432,
                          "end": 1622,
                          "loc": {
                            "start": {
                              "line": 57,
                              "column": 4
                            },
                            "end": {
                              "line": 61,
                              "column": 7
                            }
                          }
                        }
                      ],
                      "trailingComments": [
                        {
                          "type": "CommentBlock",
                          "value": "*\n     * The number of line segments used to create each rounded corner of the plane. Animatable.\n     * @type {number}\n     * @see https://developer.apple.com/reference/scenekit/scnplane/1524234-cornersegmentcount\n     ",
                          "start": 1654,
                          "end": 1878,
                          "loc": {
                            "start": {
                              "line": 64,
                              "column": 4
                            },
                            "end": {
                              "line": 68,
                              "column": 7
                            }
                          }
                        }
                      ]
                    },
                    {
                      "type": "ExpressionStatement",
                      "start": 1883,
                      "end": 1910,
                      "loc": {
                        "start": {
                          "line": 69,
                          "column": 4
                        },
                        "end": {
                          "line": 69,
                          "column": 31
                        }
                      },
                      "expression": {
                        "type": "AssignmentExpression",
                        "start": 1883,
                        "end": 1910,
                        "loc": {
                          "start": {
                            "line": 69,
                            "column": 4
                          },
                          "end": {
                            "line": 69,
                            "column": 31
                          }
                        },
                        "operator": "=",
                        "left": {
                          "type": "MemberExpression",
                          "start": 1883,
                          "end": 1906,
                          "loc": {
                            "start": {
                              "line": 69,
                              "column": 4
                            },
                            "end": {
                              "line": 69,
                              "column": 27
                            }
                          },
                          "object": {
                            "type": "ThisExpression",
                            "start": 1883,
                            "end": 1887,
                            "loc": {
                              "start": {
                                "line": 69,
                                "column": 4
                              },
                              "end": {
                                "line": 69,
                                "column": 8
                              }
                            },
                            "leadingComments": null
                          },
                          "property": {
                            "type": "Identifier",
                            "start": 1888,
                            "end": 1906,
                            "loc": {
                              "start": {
                                "line": 69,
                                "column": 9
                              },
                              "end": {
                                "line": 69,
                                "column": 27
                              },
                              "identifierName": "cornerSegmentCount"
                            },
                            "name": "cornerSegmentCount"
                          },
                          "computed": false,
                          "leadingComments": null
                        },
                        "right": {
                          "type": "NumericLiteral",
                          "start": 1909,
                          "end": 1910,
                          "loc": {
                            "start": {
                              "line": 69,
                              "column": 30
                            },
                            "end": {
                              "line": 69,
                              "column": 31
                            }
                          },
                          "extra": {
                            "rawValue": 0,
                            "raw": "0"
                          },
                          "value": 0
                        },
                        "leadingComments": null
                      },
                      "leadingComments": [
                        {
                          "type": "CommentBlock",
                          "value": "*\n     * The number of line segments used to create each rounded corner of the plane. Animatable.\n     * @type {number}\n     * @see https://developer.apple.com/reference/scenekit/scnplane/1524234-cornersegmentcount\n     ",
                          "start": 1654,
                          "end": 1878,
                          "loc": {
                            "start": {
                              "line": 64,
                              "column": 4
                            },
                            "end": {
                              "line": 68,
                              "column": 7
                            }
                          }
                        }
                      ]
                    }
                  ],
                  "directives": [],
                  "trailingComments": null
                },
                "leadingComments": [
                  {
                    "type": "CommentBlock",
                    "value": "*\n   * constructor\n   * @access public\n   * @returns {void}\n   ",
                    "start": 301,
                    "end": 368,
                    "loc": {
                      "start": {
                        "line": 14,
                        "column": 2
                      },
                      "end": {
                        "line": 18,
                        "column": 5
                      }
                    }
                  }
                ],
                "trailingComments": [
                  {
                    "type": "CommentLine",
                    "value": " Creating a Plane",
                    "start": 1919,
                    "end": 1938,
                    "loc": {
                      "start": {
                        "line": 73,
                        "column": 2
                      },
                      "end": {
                        "line": 73,
                        "column": 21
                      }
                    }
                  },
                  {
                    "type": "CommentBlock",
                    "value": "*\n   * Creates a plane geometry with the specified width and height.\n   * @access public\n   * @param {number} width - The width of the plane along the x-axis of its local coordinate space.\n   * @param {number} height - The height of the plane along the y-axis of its local coordinate space.\n   * @returns {void}\n   * @desc The plane is centered in its local coordinate system. For example, if you create a plane whose width and height are both 10.0, it extends from -5.0 to 5.0 along both the x- and y-axes, and the z-coordinate of all points in the plane is zero.\n   * @see https://developer.apple.com/reference/scenekit/scnplane/1523631-init\n   ",
                    "start": 1942,
                    "end": 2593,
                    "loc": {
                      "start": {
                        "line": 75,
                        "column": 2
                      },
                      "end": {
                        "line": 83,
                        "column": 5
                      }
                    }
                  }
                ]
              },
              {
                "type": "ClassMethod",
                "start": 2596,
                "end": 2621,
                "loc": {
                  "start": {
                    "line": 84,
                    "column": 2
                  },
                  "end": {
                    "line": 85,
                    "column": 3
                  }
                },
                "computed": false,
                "key": {
                  "type": "Identifier",
                  "start": 2596,
                  "end": 2600,
                  "loc": {
                    "start": {
                      "line": 84,
                      "column": 2
                    },
                    "end": {
                      "line": 84,
                      "column": 6
                    },
                    "identifierName": "init"
                  },
                  "name": "init",
                  "leadingComments": null
                },
                "static": false,
                "kind": "method",
                "id": null,
                "generator": false,
                "expression": false,
                "async": false,
                "params": [
                  {
                    "type": "Identifier",
                    "start": 2601,
                    "end": 2606,
                    "loc": {
                      "start": {
                        "line": 84,
                        "column": 7
                      },
                      "end": {
                        "line": 84,
                        "column": 12
                      },
                      "identifierName": "width"
                    },
                    "name": "width"
                  },
                  {
                    "type": "Identifier",
                    "start": 2608,
                    "end": 2614,
                    "loc": {
                      "start": {
                        "line": 84,
                        "column": 14
                      },
                      "end": {
                        "line": 84,
                        "column": 20
                      },
                      "identifierName": "height"
                    },
                    "name": "height"
                  }
                ],
                "body": {
                  "type": "BlockStatement",
                  "start": 2616,
                  "end": 2621,
                  "loc": {
                    "start": {
                      "line": 84,
                      "column": 22
                    },
                    "end": {
                      "line": 85,
                      "column": 3
                    }
                  },
                  "body": [],
                  "directives": []
                },
                "leadingComments": [
                  {
                    "type": "CommentLine",
                    "value": " Creating a Plane",
                    "start": 1919,
                    "end": 1938,
                    "loc": {
                      "start": {
                        "line": 73,
                        "column": 2
                      },
                      "end": {
                        "line": 73,
                        "column": 21
                      }
                    }
                  },
                  {
                    "type": "CommentBlock",
                    "value": "*\n   * Creates a plane geometry with the specified width and height.\n   * @access public\n   * @param {number} width - The width of the plane along the x-axis of its local coordinate space.\n   * @param {number} height - The height of the plane along the y-axis of its local coordinate space.\n   * @returns {void}\n   * @desc The plane is centered in its local coordinate system. For example, if you create a plane whose width and height are both 10.0, it extends from -5.0 to 5.0 along both the x- and y-axes, and the z-coordinate of all points in the plane is zero.\n   * @see https://developer.apple.com/reference/scenekit/scnplane/1523631-init\n   ",
                    "start": 1942,
                    "end": 2593,
                    "loc": {
                      "start": {
                        "line": 75,
                        "column": 2
                      },
                      "end": {
                        "line": 83,
                        "column": 5
                      }
                    }
                  }
                ]
              }
            ]
          },
          "leadingComments": [
            {
              "type": "CommentBlock",
              "value": "*\n * A rectangular, one-sided plane geometry of specified width and height.\n * @access public\n * @extends {SCNGeometry}\n * @see https://developer.apple.com/reference/scenekit/scnplane\n ",
              "start": 56,
              "end": 245,
              "loc": {
                "start": {
                  "line": 6,
                  "column": 0
                },
                "end": {
                  "line": 11,
                  "column": 3
                }
              }
            }
          ],
          "trailingComments": []
        },
        "leadingComments": [
          {
            "type": "CommentBlock",
            "value": "*\n * A rectangular, one-sided plane geometry of specified width and height.\n * @access public\n * @extends {SCNGeometry}\n * @see https://developer.apple.com/reference/scenekit/scnplane\n ",
            "start": 56,
            "end": 245,
            "loc": {
              "start": {
                "line": 6,
                "column": 0
              },
              "end": {
                "line": 11,
                "column": 3
              }
            }
          }
        ]
      }
    ],
    "directives": [
      {
        "type": "Directive",
        "start": 0,
        "end": 12,
        "loc": {
          "start": {
            "line": 1,
            "column": 0
          },
          "end": {
            "line": 1,
            "column": 12
          }
        },
        "value": {
          "type": "DirectiveLiteral",
          "start": 0,
          "end": 12,
          "loc": {
            "start": {
              "line": 1,
              "column": 0
            },
            "end": {
              "line": 1,
              "column": 12
            }
          },
          "value": "use strict",
          "extra": {
            "raw": "'use strict'",
            "rawValue": "use strict"
          }
        }
      }
    ]
  },
  "comments": [
    {
      "type": "CommentBlock",
      "value": "*\n * A rectangular, one-sided plane geometry of specified width and height.\n * @access public\n * @extends {SCNGeometry}\n * @see https://developer.apple.com/reference/scenekit/scnplane\n ",
      "start": 56,
      "end": 245,
      "loc": {
        "start": {
          "line": 6,
          "column": 0
        },
        "end": {
          "line": 11,
          "column": 3
        }
      }
    },
    {
      "type": "CommentBlock",
      "value": "*\n   * constructor\n   * @access public\n   * @returns {void}\n   ",
      "start": 301,
      "end": 368,
      "loc": {
        "start": {
          "line": 14,
          "column": 2
        },
        "end": {
          "line": 18,
          "column": 5
        }
      }
    },
    {
      "type": "CommentLine",
      "value": " Adjusting a Plane’s Dimensions",
      "start": 385,
      "end": 418,
      "loc": {
        "start": {
          "line": 21,
          "column": 4
        },
        "end": {
          "line": 21,
          "column": 37
        }
      }
    },
    {
      "type": "CommentBlock",
      "value": "*\n     * The extent of the plane along its horizontal axis. Animatable.\n     * @type {number}\n     * @see https://developer.apple.com/reference/scenekit/scnplane/1523782-width\n     ",
      "start": 424,
      "end": 609,
      "loc": {
        "start": {
          "line": 23,
          "column": 4
        },
        "end": {
          "line": 27,
          "column": 7
        }
      }
    },
    {
      "type": "CommentBlock",
      "value": "*\n     * The extent of the plane along its vertical axis. Animatable.\n     * @type {number}\n     * @see https://developer.apple.com/reference/scenekit/scnplane/1522837-height\n     ",
      "start": 634,
      "end": 818,
      "loc": {
        "start": {
          "line": 30,
          "column": 4
        },
        "end": {
          "line": 34,
          "column": 7
        }
      }
    },
    {
      "type": "CommentLine",
      "value": " Adjusting Geometric Detail",
      "start": 845,
      "end": 874,
      "loc": {
        "start": {
          "line": 38,
          "column": 4
        },
        "end": {
          "line": 38,
          "column": 33
        }
      }
    },
    {
      "type": "CommentBlock",
      "value": "*\n     * The number of subdivisions in the plane’s surface along its horizontal axis. Animatable.\n     * @type {number}\n     * @see https://developer.apple.com/reference/scenekit/scnplane/1523991-widthsegmentcount\n     ",
      "start": 880,
      "end": 1103,
      "loc": {
        "start": {
          "line": 40,
          "column": 4
        },
        "end": {
          "line": 44,
          "column": 7
        }
      }
    },
    {
      "type": "CommentBlock",
      "value": "*\n     * The number of subdivisions in the plane’s surface along its vertical axis. Animatable.\n     * @type {number}\n     * @see https://developer.apple.com/reference/scenekit/scnplane/1522889-heightsegmentcount\n     ",
      "start": 1140,
      "end": 1362,
      "loc": {
        "start": {
          "line": 47,
          "column": 4
        },
        "end": {
          "line": 51,
          "column": 7
        }
      }
    },
    {
      "type": "CommentLine",
      "value": " Adding Rounded Corners",
      "start": 1401,
      "end": 1426,
      "loc": {
        "start": {
          "line": 55,
          "column": 4
        },
        "end": {
          "line": 55,
          "column": 29
        }
      }
    },
    {
      "type": "CommentBlock",
      "value": "*\n     * The radius of curvature for the plane’s corners. Animatable.\n     * @type {number}\n     * @see https://developer.apple.com/reference/scenekit/scnplane/1523005-cornerradius\n     ",
      "start": 1432,
      "end": 1622,
      "loc": {
        "start": {
          "line": 57,
          "column": 4
        },
        "end": {
          "line": 61,
          "column": 7
        }
      }
    },
    {
      "type": "CommentBlock",
      "value": "*\n     * The number of line segments used to create each rounded corner of the plane. Animatable.\n     * @type {number}\n     * @see https://developer.apple.com/reference/scenekit/scnplane/1524234-cornersegmentcount\n     ",
      "start": 1654,
      "end": 1878,
      "loc": {
        "start": {
          "line": 64,
          "column": 4
        },
        "end": {
          "line": 68,
          "column": 7
        }
      }
    },
    {
      "type": "CommentLine",
      "value": " Creating a Plane",
      "start": 1919,
      "end": 1938,
      "loc": {
        "start": {
          "line": 73,
          "column": 2
        },
        "end": {
          "line": 73,
          "column": 21
        }
      }
    },
    {
      "type": "CommentBlock",
      "value": "*\n   * Creates a plane geometry with the specified width and height.\n   * @access public\n   * @param {number} width - The width of the plane along the x-axis of its local coordinate space.\n   * @param {number} height - The height of the plane along the y-axis of its local coordinate space.\n   * @returns {void}\n   * @desc The plane is centered in its local coordinate system. For example, if you create a plane whose width and height are both 10.0, it extends from -5.0 to 5.0 along both the x- and y-axes, and the z-coordinate of all points in the plane is zero.\n   * @see https://developer.apple.com/reference/scenekit/scnplane/1523631-init\n   ",
      "start": 1942,
      "end": 2593,
      "loc": {
        "start": {
          "line": 75,
          "column": 2
        },
        "end": {
          "line": 83,
          "column": 5
        }
      }
    }
  ],
  "tokens": [
    {
      "type": {
        "label": "string",
        "beforeExpr": false,
        "startsExpr": true,
        "rightAssociative": false,
        "isLoop": false,
        "isAssign": false,
        "prefix": false,
        "postfix": false,
        "binop": null,
        "updateContext": null
      },
      "value": "use strict",
      "start": 0,
      "end": 12,
      "loc": {
        "start": {
          "line": 1,
          "column": 0
        },
        "end": {
          "line": 1,
          "column": 12
        }
      }
    },
    {
      "type": {
        "label": "import",
        "keyword": "import",
        "beforeExpr": false,
        "startsExpr": false,
        "rightAssociative": false,
        "isLoop": false,
        "isAssign": false,
        "prefix": false,
        "postfix": false,
        "binop": null,
        "updateContext": null
      },
      "value": "import",
      "start": 14,
      "end": 20,
      "loc": {
        "start": {
          "line": 3,
          "column": 0
        },
        "end": {
          "line": 3,
          "column": 6
        }
      }
    },
    {
      "type": {
        "label": "name",
        "beforeExpr": false,
        "startsExpr": true,
        "rightAssociative": false,
        "isLoop": false,
        "isAssign": false,
        "prefix": false,
        "postfix": false,
        "binop": null
      },
      "value": "SCNGeometry",
      "start": 21,
      "end": 32,
      "loc": {
        "start": {
          "line": 3,
          "column": 7
        },
        "end": {
          "line": 3,
          "column": 18
        }
      }
    },
    {
      "type": {
        "label": "name",
        "beforeExpr": false,
        "startsExpr": true,
        "rightAssociative": false,
        "isLoop": false,
        "isAssign": false,
        "prefix": false,
        "postfix": false,
        "binop": null
      },
      "value": "from",
      "start": 33,
      "end": 37,
      "loc": {
        "start": {
          "line": 3,
          "column": 19
        },
        "end": {
          "line": 3,
          "column": 23
        }
      }
    },
    {
      "type": {
        "label": "string",
        "beforeExpr": false,
        "startsExpr": true,
        "rightAssociative": false,
        "isLoop": false,
        "isAssign": false,
        "prefix": false,
        "postfix": false,
        "binop": null,
        "updateContext": null
      },
      "value": "./SCNGeometry",
      "start": 38,
      "end": 53,
      "loc": {
        "start": {
          "line": 3,
          "column": 24
        },
        "end": {
          "line": 3,
          "column": 39
        }
      }
    },
    {
      "type": "CommentBlock",
      "value": "*\n * A rectangular, one-sided plane geometry of specified width and height.\n * @access public\n * @extends {SCNGeometry}\n * @see https://developer.apple.com/reference/scenekit/scnplane\n ",
      "start": 56,
      "end": 245,
      "loc": {
        "start": {
          "line": 6,
          "column": 0
        },
        "end": {
          "line": 11,
          "column": 3
        }
      }
    },
    {
      "type": {
        "label": "export",
        "keyword": "export",
        "beforeExpr": false,
        "startsExpr": false,
        "rightAssociative": false,
        "isLoop": false,
        "isAssign": false,
        "prefix": false,
        "postfix": false,
        "binop": null,
        "updateContext": null
      },
      "value": "export",
      "start": 246,
      "end": 252,
      "loc": {
        "start": {
          "line": 12,
          "column": 0
        },
        "end": {
          "line": 12,
          "column": 6
        }
      }
    },
    {
      "type": {
        "label": "default",
        "keyword": "default",
        "beforeExpr": true,
        "startsExpr": false,
        "rightAssociative": false,
        "isLoop": false,
        "isAssign": false,
        "prefix": false,
        "postfix": false,
        "binop": null,
        "updateContext": null
      },
      "value": "default",
      "start": 253,
      "end": 260,
      "loc": {
        "start": {
          "line": 12,
          "column": 7
        },
        "end": {
          "line": 12,
          "column": 14
        }
      }
    },
    {
      "type": {
        "label": "class",
        "keyword": "class",
        "beforeExpr": false,
        "startsExpr": false,
        "rightAssociative": false,
        "isLoop": false,
        "isAssign": false,
        "prefix": false,
        "postfix": false,
        "binop": null,
        "updateContext": null
      },
      "value": "class",
      "start": 261,
      "end": 266,
      "loc": {
        "start": {
          "line": 12,
          "column": 15
        },
        "end": {
          "line": 12,
          "column": 20
        }
      }
    },
    {
      "type": {
        "label": "name",
        "beforeExpr": false,
        "startsExpr": true,
        "rightAssociative": false,
        "isLoop": false,
        "isAssign": false,
        "prefix": false,
        "postfix": false,
        "binop": null
      },
      "value": "SCNPlane",
      "start": 267,
      "end": 275,
      "loc": {
        "start": {
          "line": 12,
          "column": 21
        },
        "end": {
          "line": 12,
          "column": 29
        }
      }
    },
    {
      "type": {
        "label": "extends",
        "keyword": "extends",
        "beforeExpr": true,
        "startsExpr": false,
        "rightAssociative": false,
        "isLoop": false,
        "isAssign": false,
        "prefix": false,
        "postfix": false,
        "binop": null,
        "updateContext": null
      },
      "value": "extends",
      "start": 276,
      "end": 283,
      "loc": {
        "start": {
          "line": 12,
          "column": 30
        },
        "end": {
          "line": 12,
          "column": 37
        }
      }
    },
    {
      "type": {
        "label": "name",
        "beforeExpr": false,
        "startsExpr": true,
        "rightAssociative": false,
        "isLoop": false,
        "isAssign": false,
        "prefix": false,
        "postfix": false,
        "binop": null
      },
      "value": "SCNGeometry",
      "start": 284,
      "end": 295,
      "loc": {
        "start": {
          "line": 12,
          "column": 38
        },
        "end": {
          "line": 12,
          "column": 49
        }
      }
    },
    {
      "type": {
        "label": "{",
        "beforeExpr": true,
        "startsExpr": true,
        "rightAssociative": false,
        "isLoop": false,
        "isAssign": false,
        "prefix": false,
        "postfix": false,
        "binop": null
      },
      "start": 296,
      "end": 297,
      "loc": {
        "start": {
          "line": 12,
          "column": 50
        },
        "end": {
          "line": 12,
          "column": 51
        }
      }
    },
    {
      "type": "CommentBlock",
      "value": "*\n   * constructor\n   * @access public\n   * @returns {void}\n   ",
      "start": 301,
      "end": 368,
      "loc": {
        "start": {
          "line": 14,
          "column": 2
        },
        "end": {
          "line": 18,
          "column": 5
        }
      }
    },
    {
      "type": {
        "label": "name",
        "beforeExpr": false,
        "startsExpr": true,
        "rightAssociative": false,
        "isLoop": false,
        "isAssign": false,
        "prefix": false,
        "postfix": false,
        "binop": null
      },
      "value": "init",
      "start": 371,
      "end": 375,
      "loc": {
        "start": {
          "line": 19,
          "column": 2
        },
        "end": {
          "line": 19,
          "column": 6
        }
      }
    },
    {
      "type": {
        "label": "(",
        "beforeExpr": true,
        "startsExpr": true,
        "rightAssociative": false,
        "isLoop": false,
        "isAssign": false,
        "prefix": false,
        "postfix": false,
        "binop": null
      },
      "start": 375,
      "end": 376,
      "loc": {
        "start": {
          "line": 19,
          "column": 6
        },
        "end": {
          "line": 19,
          "column": 7
        }
      }
    },
    {
      "type": {
        "label": ")",
        "beforeExpr": false,
        "startsExpr": false,
        "rightAssociative": false,
        "isLoop": false,
        "isAssign": false,
        "prefix": false,
        "postfix": false,
        "binop": null
      },
      "start": 376,
      "end": 377,
      "loc": {
        "start": {
          "line": 19,
          "column": 7
        },
        "end": {
          "line": 19,
          "column": 8
        }
      }
    },
    {
      "type": {
        "label": "{",
        "beforeExpr": true,
        "startsExpr": true,
        "rightAssociative": false,
        "isLoop": false,
        "isAssign": false,
        "prefix": false,
        "postfix": false,
        "binop": null
      },
      "start": 378,
      "end": 379,
      "loc": {
        "start": {
          "line": 19,
          "column": 9
        },
        "end": {
          "line": 19,
          "column": 10
        }
      }
    },
    {
      "type": "CommentLine",
      "value": " Adjusting a Plane’s Dimensions",
      "start": 385,
      "end": 418,
      "loc": {
        "start": {
          "line": 21,
          "column": 4
        },
        "end": {
          "line": 21,
          "column": 37
        }
      }
    },
    {
      "type": "CommentBlock",
      "value": "*\n     * The extent of the plane along its horizontal axis. Animatable.\n     * @type {number}\n     * @see https://developer.apple.com/reference/scenekit/scnplane/1523782-width\n     ",
      "start": 424,
      "end": 609,
      "loc": {
        "start": {
          "line": 23,
          "column": 4
        },
        "end": {
          "line": 27,
          "column": 7
        }
      }
    },
    {
      "type": {
        "label": "this",
        "keyword": "this",
        "beforeExpr": false,
        "startsExpr": true,
        "rightAssociative": false,
        "isLoop": false,
        "isAssign": false,
        "prefix": false,
        "postfix": false,
        "binop": null,
        "updateContext": null
      },
      "value": "this",
      "start": 614,
      "end": 618,
      "loc": {
        "start": {
          "line": 28,
          "column": 4
        },
        "end": {
          "line": 28,
          "column": 8
        }
      }
    },
    {
      "type": {
        "label": ".",
        "beforeExpr": false,
        "startsExpr": false,
        "rightAssociative": false,
        "isLoop": false,
        "isAssign": false,
        "prefix": false,
        "postfix": false,
        "binop": null,
        "updateContext": null
      },
      "start": 618,
      "end": 619,
      "loc": {
        "start": {
          "line": 28,
          "column": 8
        },
        "end": {
          "line": 28,
          "column": 9
        }
      }
    },
    {
      "type": {
        "label": "name",
        "beforeExpr": false,
        "startsExpr": true,
        "rightAssociative": false,
        "isLoop": false,
        "isAssign": false,
        "prefix": false,
        "postfix": false,
        "binop": null
      },
      "value": "width",
      "start": 619,
      "end": 624,
      "loc": {
        "start": {
          "line": 28,
          "column": 9
        },
        "end": {
          "line": 28,
          "column": 14
        }
      }
    },
    {
      "type": {
        "label": "=",
        "beforeExpr": true,
        "startsExpr": false,
        "rightAssociative": false,
        "isLoop": false,
        "isAssign": true,
        "prefix": false,
        "postfix": false,
        "binop": null,
        "updateContext": null
      },
      "value": "=",
      "start": 625,
      "end": 626,
      "loc": {
        "start": {
          "line": 28,
          "column": 15
        },
        "end": {
          "line": 28,
          "column": 16
        }
      }
    },
    {
      "type": {
        "label": "num",
        "beforeExpr": false,
        "startsExpr": true,
        "rightAssociative": false,
        "isLoop": false,
        "isAssign": false,
        "prefix": false,
        "postfix": false,
        "binop": null,
        "updateContext": null
      },
      "value": 0,
      "start": 627,
      "end": 628,
      "loc": {
        "start": {
          "line": 28,
          "column": 17
        },
        "end": {
          "line": 28,
          "column": 18
        }
      }
    },
    {
      "type": "CommentBlock",
      "value": "*\n     * The extent of the plane along its vertical axis. Animatable.\n     * @type {number}\n     * @see https://developer.apple.com/reference/scenekit/scnplane/1522837-height\n     ",
      "start": 634,
      "end": 818,
      "loc": {
        "start": {
          "line": 30,
          "column": 4
        },
        "end": {
          "line": 34,
          "column": 7
        }
      }
    },
    {
      "type": {
        "label": "this",
        "keyword": "this",
        "beforeExpr": false,
        "startsExpr": true,
        "rightAssociative": false,
        "isLoop": false,
        "isAssign": false,
        "prefix": false,
        "postfix": false,
        "binop": null,
        "updateContext": null
      },
      "value": "this",
      "start": 823,
      "end": 827,
      "loc": {
        "start": {
          "line": 35,
          "column": 4
        },
        "end": {
          "line": 35,
          "column": 8
        }
      }
    },
    {
      "type": {
        "label": ".",
        "beforeExpr": false,
        "startsExpr": false,
        "rightAssociative": false,
        "isLoop": false,
        "isAssign": false,
        "prefix": false,
        "postfix": false,
        "binop": null,
        "updateContext": null
      },
      "start": 827,
      "end": 828,
      "loc": {
        "start": {
          "line": 35,
          "column": 8
        },
        "end": {
          "line": 35,
          "column": 9
        }
      }
    },
    {
      "type": {
        "label": "name",
        "beforeExpr": false,
        "startsExpr": true,
        "rightAssociative": false,
        "isLoop": false,
        "isAssign": false,
        "prefix": false,
        "postfix": false,
        "binop": null
      },
      "value": "height",
      "start": 828,
      "end": 834,
      "loc": {
        "start": {
          "line": 35,
          "column": 9
        },
        "end": {
          "line": 35,
          "column": 15
        }
      }
    },
    {
      "type": {
        "label": "=",
        "beforeExpr": true,
        "startsExpr": false,
        "rightAssociative": false,
        "isLoop": false,
        "isAssign": true,
        "prefix": false,
        "postfix": false,
        "binop": null,
        "updateContext": null
      },
      "value": "=",
      "start": 835,
      "end": 836,
      "loc": {
        "start": {
          "line": 35,
          "column": 16
        },
        "end": {
          "line": 35,
          "column": 17
        }
      }
    },
    {
      "type": {
        "label": "num",
        "beforeExpr": false,
        "startsExpr": true,
        "rightAssociative": false,
        "isLoop": false,
        "isAssign": false,
        "prefix": false,
        "postfix": false,
        "binop": null,
        "updateContext": null
      },
      "value": 0,
      "start": 837,
      "end": 838,
      "loc": {
        "start": {
          "line": 35,
          "column": 18
        },
        "end": {
          "line": 35,
          "column": 19
        }
      }
    },
    {
      "type": "CommentLine",
      "value": " Adjusting Geometric Detail",
      "start": 845,
      "end": 874,
      "loc": {
        "start": {
          "line": 38,
          "column": 4
        },
        "end": {
          "line": 38,
          "column": 33
        }
      }
    },
    {
      "type": "CommentBlock",
      "value": "*\n     * The number of subdivisions in the plane’s surface along its horizontal axis. Animatable.\n     * @type {number}\n     * @see https://developer.apple.com/reference/scenekit/scnplane/1523991-widthsegmentcount\n     ",
      "start": 880,
      "end": 1103,
      "loc": {
        "start": {
          "line": 40,
          "column": 4
        },
        "end": {
          "line": 44,
          "column": 7
        }
      }
    },
    {
      "type": {
        "label": "this",
        "keyword": "this",
        "beforeExpr": false,
        "startsExpr": true,
        "rightAssociative": false,
        "isLoop": false,
        "isAssign": false,
        "prefix": false,
        "postfix": false,
        "binop": null,
        "updateContext": null
      },
      "value": "this",
      "start": 1108,
      "end": 1112,
      "loc": {
        "start": {
          "line": 45,
          "column": 4
        },
        "end": {
          "line": 45,
          "column": 8
        }
      }
    },
    {
      "type": {
        "label": ".",
        "beforeExpr": false,
        "startsExpr": false,
        "rightAssociative": false,
        "isLoop": false,
        "isAssign": false,
        "prefix": false,
        "postfix": false,
        "binop": null,
        "updateContext": null
      },
      "start": 1112,
      "end": 1113,
      "loc": {
        "start": {
          "line": 45,
          "column": 8
        },
        "end": {
          "line": 45,
          "column": 9
        }
      }
    },
    {
      "type": {
        "label": "name",
        "beforeExpr": false,
        "startsExpr": true,
        "rightAssociative": false,
        "isLoop": false,
        "isAssign": false,
        "prefix": false,
        "postfix": false,
        "binop": null
      },
      "value": "widthSegmentCount",
      "start": 1113,
      "end": 1130,
      "loc": {
        "start": {
          "line": 45,
          "column": 9
        },
        "end": {
          "line": 45,
          "column": 26
        }
      }
    },
    {
      "type": {
        "label": "=",
        "beforeExpr": true,
        "startsExpr": false,
        "rightAssociative": false,
        "isLoop": false,
        "isAssign": true,
        "prefix": false,
        "postfix": false,
        "binop": null,
        "updateContext": null
      },
      "value": "=",
      "start": 1131,
      "end": 1132,
      "loc": {
        "start": {
          "line": 45,
          "column": 27
        },
        "end": {
          "line": 45,
          "column": 28
        }
      }
    },
    {
      "type": {
        "label": "num",
        "beforeExpr": false,
        "startsExpr": true,
        "rightAssociative": false,
        "isLoop": false,
        "isAssign": false,
        "prefix": false,
        "postfix": false,
        "binop": null,
        "updateContext": null
      },
      "value": 0,
      "start": 1133,
      "end": 1134,
      "loc": {
        "start": {
          "line": 45,
          "column": 29
        },
        "end": {
          "line": 45,
          "column": 30
        }
      }
    },
    {
      "type": "CommentBlock",
      "value": "*\n     * The number of subdivisions in the plane’s surface along its vertical axis. Animatable.\n     * @type {number}\n     * @see https://developer.apple.com/reference/scenekit/scnplane/1522889-heightsegmentcount\n     ",
      "start": 1140,
      "end": 1362,
      "loc": {
        "start": {
          "line": 47,
          "column": 4
        },
        "end": {
          "line": 51,
          "column": 7
        }
      }
    },
    {
      "type": {
        "label": "this",
        "keyword": "this",
        "beforeExpr": false,
        "startsExpr": true,
        "rightAssociative": false,
        "isLoop": false,
        "isAssign": false,
        "prefix": false,
        "postfix": false,
        "binop": null,
        "updateContext": null
      },
      "value": "this",
      "start": 1367,
      "end": 1371,
      "loc": {
        "start": {
          "line": 52,
          "column": 4
        },
        "end": {
          "line": 52,
          "column": 8
        }
      }
    },
    {
      "type": {
        "label": ".",
        "beforeExpr": false,
        "startsExpr": false,
        "rightAssociative": false,
        "isLoop": false,
        "isAssign": false,
        "prefix": false,
        "postfix": false,
        "binop": null,
        "updateContext": null
      },
      "start": 1371,
      "end": 1372,
      "loc": {
        "start": {
          "line": 52,
          "column": 8
        },
        "end": {
          "line": 52,
          "column": 9
        }
      }
    },
    {
      "type": {
        "label": "name",
        "beforeExpr": false,
        "startsExpr": true,
        "rightAssociative": false,
        "isLoop": false,
        "isAssign": false,
        "prefix": false,
        "postfix": false,
        "binop": null
      },
      "value": "heightSegmentCount",
      "start": 1372,
      "end": 1390,
      "loc": {
        "start": {
          "line": 52,
          "column": 9
        },
        "end": {
          "line": 52,
          "column": 27
        }
      }
    },
    {
      "type": {
        "label": "=",
        "beforeExpr": true,
        "startsExpr": false,
        "rightAssociative": false,
        "isLoop": false,
        "isAssign": true,
        "prefix": false,
        "postfix": false,
        "binop": null,
        "updateContext": null
      },
      "value": "=",
      "start": 1391,
      "end": 1392,
      "loc": {
        "start": {
          "line": 52,
          "column": 28
        },
        "end": {
          "line": 52,
          "column": 29
        }
      }
    },
    {
      "type": {
        "label": "num",
        "beforeExpr": false,
        "startsExpr": true,
        "rightAssociative": false,
        "isLoop": false,
        "isAssign": false,
        "prefix": false,
        "postfix": false,
        "binop": null,
        "updateContext": null
      },
      "value": 0,
      "start": 1393,
      "end": 1394,
      "loc": {
        "start": {
          "line": 52,
          "column": 30
        },
        "end": {
          "line": 52,
          "column": 31
        }
      }
    },
    {
      "type": "CommentLine",
      "value": " Adding Rounded Corners",
      "start": 1401,
      "end": 1426,
      "loc": {
        "start": {
          "line": 55,
          "column": 4
        },
        "end": {
          "line": 55,
          "column": 29
        }
      }
    },
    {
      "type": "CommentBlock",
      "value": "*\n     * The radius of curvature for the plane’s corners. Animatable.\n     * @type {number}\n     * @see https://developer.apple.com/reference/scenekit/scnplane/1523005-cornerradius\n     ",
      "start": 1432,
      "end": 1622,
      "loc": {
        "start": {
          "line": 57,
          "column": 4
        },
        "end": {
          "line": 61,
          "column": 7
        }
      }
    },
    {
      "type": {
        "label": "this",
        "keyword": "this",
        "beforeExpr": false,
        "startsExpr": true,
        "rightAssociative": false,
        "isLoop": false,
        "isAssign": false,
        "prefix": false,
        "postfix": false,
        "binop": null,
        "updateContext": null
      },
      "value": "this",
      "start": 1627,
      "end": 1631,
      "loc": {
        "start": {
          "line": 62,
          "column": 4
        },
        "end": {
          "line": 62,
          "column": 8
        }
      }
    },
    {
      "type": {
        "label": ".",
        "beforeExpr": false,
        "startsExpr": false,
        "rightAssociative": false,
        "isLoop": false,
        "isAssign": false,
        "prefix": false,
        "postfix": false,
        "binop": null,
        "updateContext": null
      },
      "start": 1631,
      "end": 1632,
      "loc": {
        "start": {
          "line": 62,
          "column": 8
        },
        "end": {
          "line": 62,
          "column": 9
        }
      }
    },
    {
      "type": {
        "label": "name",
        "beforeExpr": false,
        "startsExpr": true,
        "rightAssociative": false,
        "isLoop": false,
        "isAssign": false,
        "prefix": false,
        "postfix": false,
        "binop": null
      },
      "value": "cornerRadius",
      "start": 1632,
      "end": 1644,
      "loc": {
        "start": {
          "line": 62,
          "column": 9
        },
        "end": {
          "line": 62,
          "column": 21
        }
      }
    },
    {
      "type": {
        "label": "=",
        "beforeExpr": true,
        "startsExpr": false,
        "rightAssociative": false,
        "isLoop": false,
        "isAssign": true,
        "prefix": false,
        "postfix": false,
        "binop": null,
        "updateContext": null
      },
      "value": "=",
      "start": 1645,
      "end": 1646,
      "loc": {
        "start": {
          "line": 62,
          "column": 22
        },
        "end": {
          "line": 62,
          "column": 23
        }
      }
    },
    {
      "type": {
        "label": "num",
        "beforeExpr": false,
        "startsExpr": true,
        "rightAssociative": false,
        "isLoop": false,
        "isAssign": false,
        "prefix": false,
        "postfix": false,
        "binop": null,
        "updateContext": null
      },
      "value": 0,
      "start": 1647,
      "end": 1648,
      "loc": {
        "start": {
          "line": 62,
          "column": 24
        },
        "end": {
          "line": 62,
          "column": 25
        }
      }
    },
    {
      "type": "CommentBlock",
      "value": "*\n     * The number of line segments used to create each rounded corner of the plane. Animatable.\n     * @type {number}\n     * @see https://developer.apple.com/reference/scenekit/scnplane/1524234-cornersegmentcount\n     ",
      "start": 1654,
      "end": 1878,
      "loc": {
        "start": {
          "line": 64,
          "column": 4
        },
        "end": {
          "line": 68,
          "column": 7
        }
      }
    },
    {
      "type": {
        "label": "this",
        "keyword": "this",
        "beforeExpr": false,
        "startsExpr": true,
        "rightAssociative": false,
        "isLoop": false,
        "isAssign": false,
        "prefix": false,
        "postfix": false,
        "binop": null,
        "updateContext": null
      },
      "value": "this",
      "start": 1883,
      "end": 1887,
      "loc": {
        "start": {
          "line": 69,
          "column": 4
        },
        "end": {
          "line": 69,
          "column": 8
        }
      }
    },
    {
      "type": {
        "label": ".",
        "beforeExpr": false,
        "startsExpr": false,
        "rightAssociative": false,
        "isLoop": false,
        "isAssign": false,
        "prefix": false,
        "postfix": false,
        "binop": null,
        "updateContext": null
      },
      "start": 1887,
      "end": 1888,
      "loc": {
        "start": {
          "line": 69,
          "column": 8
        },
        "end": {
          "line": 69,
          "column": 9
        }
      }
    },
    {
      "type": {
        "label": "name",
        "beforeExpr": false,
        "startsExpr": true,
        "rightAssociative": false,
        "isLoop": false,
        "isAssign": false,
        "prefix": false,
        "postfix": false,
        "binop": null
      },
      "value": "cornerSegmentCount",
      "start": 1888,
      "end": 1906,
      "loc": {
        "start": {
          "line": 69,
          "column": 9
        },
        "end": {
          "line": 69,
          "column": 27
        }
      }
    },
    {
      "type": {
        "label": "=",
        "beforeExpr": true,
        "startsExpr": false,
        "rightAssociative": false,
        "isLoop": false,
        "isAssign": true,
        "prefix": false,
        "postfix": false,
        "binop": null,
        "updateContext": null
      },
      "value": "=",
      "start": 1907,
      "end": 1908,
      "loc": {
        "start": {
          "line": 69,
          "column": 28
        },
        "end": {
          "line": 69,
          "column": 29
        }
      }
    },
    {
      "type": {
        "label": "num",
        "beforeExpr": false,
        "startsExpr": true,
        "rightAssociative": false,
        "isLoop": false,
        "isAssign": false,
        "prefix": false,
        "postfix": false,
        "binop": null,
        "updateContext": null
      },
      "value": 0,
      "start": 1909,
      "end": 1910,
      "loc": {
        "start": {
          "line": 69,
          "column": 30
        },
        "end": {
          "line": 69,
          "column": 31
        }
      }
    },
    {
      "type": {
        "label": "}",
        "beforeExpr": false,
        "startsExpr": false,
        "rightAssociative": false,
        "isLoop": false,
        "isAssign": false,
        "prefix": false,
        "postfix": false,
        "binop": null
      },
      "start": 1914,
      "end": 1915,
      "loc": {
        "start": {
          "line": 71,
          "column": 2
        },
        "end": {
          "line": 71,
          "column": 3
        }
      }
    },
    {
      "type": "CommentLine",
      "value": " Creating a Plane",
      "start": 1919,
      "end": 1938,
      "loc": {
        "start": {
          "line": 73,
          "column": 2
        },
        "end": {
          "line": 73,
          "column": 21
        }
      }
    },
    {
      "type": "CommentBlock",
      "value": "*\n   * Creates a plane geometry with the specified width and height.\n   * @access public\n   * @param {number} width - The width of the plane along the x-axis of its local coordinate space.\n   * @param {number} height - The height of the plane along the y-axis of its local coordinate space.\n   * @returns {void}\n   * @desc The plane is centered in its local coordinate system. For example, if you create a plane whose width and height are both 10.0, it extends from -5.0 to 5.0 along both the x- and y-axes, and the z-coordinate of all points in the plane is zero.\n   * @see https://developer.apple.com/reference/scenekit/scnplane/1523631-init\n   ",
      "start": 1942,
      "end": 2593,
      "loc": {
        "start": {
          "line": 75,
          "column": 2
        },
        "end": {
          "line": 83,
          "column": 5
        }
      }
    },
    {
      "type": {
        "label": "name",
        "beforeExpr": false,
        "startsExpr": true,
        "rightAssociative": false,
        "isLoop": false,
        "isAssign": false,
        "prefix": false,
        "postfix": false,
        "binop": null
      },
      "value": "init",
      "start": 2596,
      "end": 2600,
      "loc": {
        "start": {
          "line": 84,
          "column": 2
        },
        "end": {
          "line": 84,
          "column": 6
        }
      }
    },
    {
      "type": {
        "label": "(",
        "beforeExpr": true,
        "startsExpr": true,
        "rightAssociative": false,
        "isLoop": false,
        "isAssign": false,
        "prefix": false,
        "postfix": false,
        "binop": null
      },
      "start": 2600,
      "end": 2601,
      "loc": {
        "start": {
          "line": 84,
          "column": 6
        },
        "end": {
          "line": 84,
          "column": 7
        }
      }
    },
    {
      "type": {
        "label": "name",
        "beforeExpr": false,
        "startsExpr": true,
        "rightAssociative": false,
        "isLoop": false,
        "isAssign": false,
        "prefix": false,
        "postfix": false,
        "binop": null
      },
      "value": "width",
      "start": 2601,
      "end": 2606,
      "loc": {
        "start": {
          "line": 84,
          "column": 7
        },
        "end": {
          "line": 84,
          "column": 12
        }
      }
    },
    {
      "type": {
        "label": ",",
        "beforeExpr": true,
        "startsExpr": false,
        "rightAssociative": false,
        "isLoop": false,
        "isAssign": false,
        "prefix": false,
        "postfix": false,
        "binop": null,
        "updateContext": null
      },
      "start": 2606,
      "end": 2607,
      "loc": {
        "start": {
          "line": 84,
          "column": 12
        },
        "end": {
          "line": 84,
          "column": 13
        }
      }
    },
    {
      "type": {
        "label": "name",
        "beforeExpr": false,
        "startsExpr": true,
        "rightAssociative": false,
        "isLoop": false,
        "isAssign": false,
        "prefix": false,
        "postfix": false,
        "binop": null
      },
      "value": "height",
      "start": 2608,
      "end": 2614,
      "loc": {
        "start": {
          "line": 84,
          "column": 14
        },
        "end": {
          "line": 84,
          "column": 20
        }
      }
    },
    {
      "type": {
        "label": ")",
        "beforeExpr": false,
        "startsExpr": false,
        "rightAssociative": false,
        "isLoop": false,
        "isAssign": false,
        "prefix": false,
        "postfix": false,
        "binop": null
      },
      "start": 2614,
      "end": 2615,
      "loc": {
        "start": {
          "line": 84,
          "column": 20
        },
        "end": {
          "line": 84,
          "column": 21
        }
      }
    },
    {
      "type": {
        "label": "{",
        "beforeExpr": true,
        "startsExpr": true,
        "rightAssociative": false,
        "isLoop": false,
        "isAssign": false,
        "prefix": false,
        "postfix": false,
        "binop": null
      },
      "start": 2616,
      "end": 2617,
      "loc": {
        "start": {
          "line": 84,
          "column": 22
        },
        "end": {
          "line": 84,
          "column": 23
        }
      }
    },
    {
      "type": {
        "label": "}",
        "beforeExpr": false,
        "startsExpr": false,
        "rightAssociative": false,
        "isLoop": false,
        "isAssign": false,
        "prefix": false,
        "postfix": false,
        "binop": null
      },
      "start": 2620,
      "end": 2621,
      "loc": {
        "start": {
          "line": 85,
          "column": 2
        },
        "end": {
          "line": 85,
          "column": 3
        }
      }
    },
    {
      "type": {
        "label": "}",
        "beforeExpr": false,
        "startsExpr": false,
        "rightAssociative": false,
        "isLoop": false,
        "isAssign": false,
        "prefix": false,
        "postfix": false,
        "binop": null
      },
      "start": 2622,
      "end": 2623,
      "loc": {
        "start": {
          "line": 86,
          "column": 0
        },
        "end": {
          "line": 86,
          "column": 1
        }
      }
    },
    {
      "type": {
        "label": "eof",
        "beforeExpr": false,
        "startsExpr": false,
        "rightAssociative": false,
        "isLoop": false,
        "isAssign": false,
        "prefix": false,
        "postfix": false,
        "binop": null,
        "updateContext": null
      },
      "start": 2624,
      "end": 2624,
      "loc": {
        "start": {
          "line": 87,
          "column": 0
        },
        "end": {
          "line": 87,
          "column": 0
        }
      }
    }
  ]
}