{
  "type": "File",
  "start": 0,
  "end": 4339,
  "loc": {
    "start": {
      "line": 1,
      "column": 0
    },
    "end": {
      "line": 62,
      "column": 0
    }
  },
  "program": {
    "type": "Program",
    "start": 0,
    "end": 4339,
    "loc": {
      "start": {
        "line": 1,
        "column": 0
      },
      "end": {
        "line": 62,
        "column": 0
      }
    },
    "sourceType": "module",
    "body": [
      {
        "type": "ExportDefaultDeclaration",
        "start": 232,
        "end": 4338,
        "loc": {
          "start": {
            "line": 8,
            "column": 0
          },
          "end": {
            "line": 61,
            "column": 1
          }
        },
        "declaration": {
          "type": "ClassDeclaration",
          "start": 247,
          "end": 4338,
          "loc": {
            "start": {
              "line": 8,
              "column": 15
            },
            "end": {
              "line": 61,
              "column": 1
            }
          },
          "id": {
            "type": "Identifier",
            "start": 253,
            "end": 267,
            "loc": {
              "start": {
                "line": 8,
                "column": 21
              },
              "end": {
                "line": 8,
                "column": 35
              },
              "identifierName": "DispatchObject"
            },
            "name": "DispatchObject",
            "leadingComments": null
          },
          "superClass": null,
          "body": {
            "type": "ClassBody",
            "start": 268,
            "end": 4338,
            "loc": {
              "start": {
                "line": 8,
                "column": 36
              },
              "end": {
                "line": 61,
                "column": 1
              }
            },
            "body": [
              {
                "type": "ClassMethod",
                "start": 340,
                "end": 380,
                "loc": {
                  "start": {
                    "line": 15,
                    "column": 2
                  },
                  "end": {
                    "line": 17,
                    "column": 3
                  }
                },
                "computed": false,
                "key": {
                  "type": "Identifier",
                  "start": 340,
                  "end": 351,
                  "loc": {
                    "start": {
                      "line": 15,
                      "column": 2
                    },
                    "end": {
                      "line": 15,
                      "column": 13
                    },
                    "identifierName": "constructor"
                  },
                  "name": "constructor",
                  "leadingComments": null
                },
                "static": false,
                "kind": "constructor",
                "id": null,
                "generator": false,
                "expression": false,
                "async": false,
                "params": [],
                "body": {
                  "type": "BlockStatement",
                  "start": 354,
                  "end": 380,
                  "loc": {
                    "start": {
                      "line": 15,
                      "column": 16
                    },
                    "end": {
                      "line": 17,
                      "column": 3
                    }
                  },
                  "body": [],
                  "directives": [],
                  "leadingComments": null,
                  "trailingComments": [
                    {
                      "type": "CommentLine",
                      "value": " nothing to do",
                      "start": 360,
                      "end": 376,
                      "loc": {
                        "start": {
                          "line": 16,
                          "column": 4
                        },
                        "end": {
                          "line": 16,
                          "column": 20
                        }
                      }
                    },
                    {
                      "type": "CommentLine",
                      "value": " Instance Methods",
                      "start": 384,
                      "end": 403,
                      "loc": {
                        "start": {
                          "line": 19,
                          "column": 2
                        },
                        "end": {
                          "line": 19,
                          "column": 21
                        }
                      }
                    },
                    {
                      "type": "CommentBlock",
                      "value": "*\n   * Activates the dispatch object.\n   * @access public\n   * @returns {void}\n   * @desc Once a dispatch object has been activated, it cannot change its target queue.\n   * @see https://developer.apple.com/reference/dispatch/dispatchobject/1641002-activate\n   ",
                      "start": 407,
                      "end": 671,
                      "loc": {
                        "start": {
                          "line": 21,
                          "column": 2
                        },
                        "end": {
                          "line": 27,
                          "column": 5
                        }
                      }
                    }
                  ]
                },
                "leadingComments": [
                  {
                    "type": "CommentBlock",
                    "value": "*\n   * constructor\n   * @access public\n   * @constructor\n   ",
                    "start": 273,
                    "end": 337,
                    "loc": {
                      "start": {
                        "line": 10,
                        "column": 2
                      },
                      "end": {
                        "line": 14,
                        "column": 5
                      }
                    }
                  }
                ]
              },
              {
                "type": "ClassMethod",
                "start": 674,
                "end": 690,
                "loc": {
                  "start": {
                    "line": 28,
                    "column": 2
                  },
                  "end": {
                    "line": 29,
                    "column": 3
                  }
                },
                "computed": false,
                "key": {
                  "type": "Identifier",
                  "start": 674,
                  "end": 682,
                  "loc": {
                    "start": {
                      "line": 28,
                      "column": 2
                    },
                    "end": {
                      "line": 28,
                      "column": 10
                    },
                    "identifierName": "activate"
                  },
                  "name": "activate",
                  "leadingComments": null
                },
                "static": false,
                "kind": "method",
                "id": null,
                "generator": false,
                "expression": false,
                "async": false,
                "params": [],
                "body": {
                  "type": "BlockStatement",
                  "start": 685,
                  "end": 690,
                  "loc": {
                    "start": {
                      "line": 28,
                      "column": 13
                    },
                    "end": {
                      "line": 29,
                      "column": 3
                    }
                  },
                  "body": [],
                  "directives": [],
                  "leadingComments": null,
                  "trailingComments": null
                },
                "leadingComments": [
                  {
                    "type": "CommentLine",
                    "value": " Instance Methods",
                    "start": 384,
                    "end": 403,
                    "loc": {
                      "start": {
                        "line": 19,
                        "column": 2
                      },
                      "end": {
                        "line": 19,
                        "column": 21
                      }
                    }
                  },
                  {
                    "type": "CommentBlock",
                    "value": "*\n   * Activates the dispatch object.\n   * @access public\n   * @returns {void}\n   * @desc Once a dispatch object has been activated, it cannot change its target queue.\n   * @see https://developer.apple.com/reference/dispatch/dispatchobject/1641002-activate\n   ",
                    "start": 407,
                    "end": 671,
                    "loc": {
                      "start": {
                        "line": 21,
                        "column": 2
                      },
                      "end": {
                        "line": 27,
                        "column": 5
                      }
                    }
                  }
                ],
                "trailingComments": [
                  {
                    "type": "CommentBlock",
                    "value": "*\n   * Resume the invocation of block objects on a dispatch object.\n   * @access public\n   * @returns {void}\n   * @desc Calling this function decrements the suspension count of a suspended dispatch queue or dispatch event source object. While the count is greater than zero, the object remains suspended. When the suspension count returns to zero, any blocks submitted to the dispatch queue or any events observed by the dispatch source while suspended are delivered.With one exception, each call to resume() must balance a call to suspend(). New dispatch event source objects returned by dispatch_source_create(_:_:_:_:) have a suspension count of 1 and must be resumed before any events are delivered. This approach allows your application to fully configure the dispatch event source object prior to delivery of the first event. In all other cases, it is undefined to call resume() more times than suspend(), which would result in a negative suspension count.\n   * @see https://developer.apple.com/reference/dispatch/dispatchobject/1452929-resume\n   ",
                    "start": 694,
                    "end": 1751,
                    "loc": {
                      "start": {
                        "line": 31,
                        "column": 2
                      },
                      "end": {
                        "line": 37,
                        "column": 5
                      }
                    }
                  }
                ]
              },
              {
                "type": "ClassMethod",
                "start": 1754,
                "end": 1768,
                "loc": {
                  "start": {
                    "line": 38,
                    "column": 2
                  },
                  "end": {
                    "line": 39,
                    "column": 3
                  }
                },
                "computed": false,
                "key": {
                  "type": "Identifier",
                  "start": 1754,
                  "end": 1760,
                  "loc": {
                    "start": {
                      "line": 38,
                      "column": 2
                    },
                    "end": {
                      "line": 38,
                      "column": 8
                    },
                    "identifierName": "resume"
                  },
                  "name": "resume",
                  "leadingComments": null
                },
                "static": false,
                "kind": "method",
                "id": null,
                "generator": false,
                "expression": false,
                "async": false,
                "params": [],
                "body": {
                  "type": "BlockStatement",
                  "start": 1763,
                  "end": 1768,
                  "loc": {
                    "start": {
                      "line": 38,
                      "column": 11
                    },
                    "end": {
                      "line": 39,
                      "column": 3
                    }
                  },
                  "body": [],
                  "directives": [],
                  "leadingComments": null,
                  "trailingComments": null
                },
                "leadingComments": [
                  {
                    "type": "CommentBlock",
                    "value": "*\n   * Resume the invocation of block objects on a dispatch object.\n   * @access public\n   * @returns {void}\n   * @desc Calling this function decrements the suspension count of a suspended dispatch queue or dispatch event source object. While the count is greater than zero, the object remains suspended. When the suspension count returns to zero, any blocks submitted to the dispatch queue or any events observed by the dispatch source while suspended are delivered.With one exception, each call to resume() must balance a call to suspend(). New dispatch event source objects returned by dispatch_source_create(_:_:_:_:) have a suspension count of 1 and must be resumed before any events are delivered. This approach allows your application to fully configure the dispatch event source object prior to delivery of the first event. In all other cases, it is undefined to call resume() more times than suspend(), which would result in a negative suspension count.\n   * @see https://developer.apple.com/reference/dispatch/dispatchobject/1452929-resume\n   ",
                    "start": 694,
                    "end": 1751,
                    "loc": {
                      "start": {
                        "line": 31,
                        "column": 2
                      },
                      "end": {
                        "line": 37,
                        "column": 5
                      }
                    }
                  }
                ],
                "trailingComments": [
                  {
                    "type": "CommentBlock",
                    "value": "*\n   * Sets the target queue for the given object.\n   * @access public\n   * @param {?DispatchQueue} queue - The new target queue for the object. The queue is retained, and the previous one, if any, is released. This parameter cannot be NULL.\n   * @returns {void}\n   * @desc An object's target queue is responsible for processing the object. The target queue determines the queue on which the object's finalizer is invoked. In addition, modifying the target queue of some objects changes their behavior:Dispatch queues:A dispatch queue's priority is inherited from its target queue. Use the dispatch_get_global_queue(_:_:) function to obtain a suitable target queue of the desired priority.If you submit a block to a serial queue, and the serial queue’s target queue is a different serial queue, that block is not invoked concurrently with blocks submitted to the target queue or to any other queue with that same target queue.ImportantIf you modify the target queue for a queue, you must be careful to avoid creating cycles in the queue hierarchy.Dispatch sources:A dispatch source's target queue specifies where its event handler and cancellation handler blocks are submitted.Dispatch I/O channels:A dispatch I/O channel's target queue specifies where its I/O operations are executed. This may affect the priority of the resulting I/O operations. For example, if the channel's target queue's priority is set to DISPATCH_QUEUE_PRIORITY_BACKGROUND, then any I/O operations performed by read(offset:length:queue:ioHandler:) or write(offset:data:queue:ioHandler:) on that queue are throttled when there is I/O contention.\n   * @see https://developer.apple.com/reference/dispatch/dispatchobject/1452989-settarget\n   ",
                    "start": 1772,
                    "end": 3488,
                    "loc": {
                      "start": {
                        "line": 41,
                        "column": 2
                      },
                      "end": {
                        "line": 48,
                        "column": 5
                      }
                    }
                  }
                ]
              },
              {
                "type": "ClassMethod",
                "start": 3491,
                "end": 3513,
                "loc": {
                  "start": {
                    "line": 49,
                    "column": 2
                  },
                  "end": {
                    "line": 50,
                    "column": 3
                  }
                },
                "computed": false,
                "key": {
                  "type": "Identifier",
                  "start": 3491,
                  "end": 3500,
                  "loc": {
                    "start": {
                      "line": 49,
                      "column": 2
                    },
                    "end": {
                      "line": 49,
                      "column": 11
                    },
                    "identifierName": "setTarget"
                  },
                  "name": "setTarget",
                  "leadingComments": null
                },
                "static": false,
                "kind": "method",
                "id": null,
                "generator": false,
                "expression": false,
                "async": false,
                "params": [
                  {
                    "type": "Identifier",
                    "start": 3501,
                    "end": 3506,
                    "loc": {
                      "start": {
                        "line": 49,
                        "column": 12
                      },
                      "end": {
                        "line": 49,
                        "column": 17
                      },
                      "identifierName": "queue"
                    },
                    "name": "queue"
                  }
                ],
                "body": {
                  "type": "BlockStatement",
                  "start": 3508,
                  "end": 3513,
                  "loc": {
                    "start": {
                      "line": 49,
                      "column": 19
                    },
                    "end": {
                      "line": 50,
                      "column": 3
                    }
                  },
                  "body": [],
                  "directives": [],
                  "leadingComments": null,
                  "trailingComments": null
                },
                "leadingComments": [
                  {
                    "type": "CommentBlock",
                    "value": "*\n   * Sets the target queue for the given object.\n   * @access public\n   * @param {?DispatchQueue} queue - The new target queue for the object. The queue is retained, and the previous one, if any, is released. This parameter cannot be NULL.\n   * @returns {void}\n   * @desc An object's target queue is responsible for processing the object. The target queue determines the queue on which the object's finalizer is invoked. In addition, modifying the target queue of some objects changes their behavior:Dispatch queues:A dispatch queue's priority is inherited from its target queue. Use the dispatch_get_global_queue(_:_:) function to obtain a suitable target queue of the desired priority.If you submit a block to a serial queue, and the serial queue’s target queue is a different serial queue, that block is not invoked concurrently with blocks submitted to the target queue or to any other queue with that same target queue.ImportantIf you modify the target queue for a queue, you must be careful to avoid creating cycles in the queue hierarchy.Dispatch sources:A dispatch source's target queue specifies where its event handler and cancellation handler blocks are submitted.Dispatch I/O channels:A dispatch I/O channel's target queue specifies where its I/O operations are executed. This may affect the priority of the resulting I/O operations. For example, if the channel's target queue's priority is set to DISPATCH_QUEUE_PRIORITY_BACKGROUND, then any I/O operations performed by read(offset:length:queue:ioHandler:) or write(offset:data:queue:ioHandler:) on that queue are throttled when there is I/O contention.\n   * @see https://developer.apple.com/reference/dispatch/dispatchobject/1452989-settarget\n   ",
                    "start": 1772,
                    "end": 3488,
                    "loc": {
                      "start": {
                        "line": 41,
                        "column": 2
                      },
                      "end": {
                        "line": 48,
                        "column": 5
                      }
                    }
                  }
                ],
                "trailingComments": [
                  {
                    "type": "CommentBlock",
                    "value": "*\n   * Suspends the invocation of block objects on a dispatch object.\n   * @access public\n   * @returns {void}\n   * @desc By suspending a dispatch object, your application can temporarily prevent the execution of any blocks associated with that object. The suspension occurs after completion of any blocks running at the time of the call. Calling this function increments the suspension count of the object, and calling resume() decrements it. While the count is greater than zero, the object remains suspended, so you must balance each suspend() call with a matching resume() call.Any blocks submitted to a dispatch queue or events observed by a dispatch source are delivered once the object is resumed. \n   * @see https://developer.apple.com/reference/dispatch/dispatchobject/1452801-suspend\n   ",
                    "start": 3517,
                    "end": 4318,
                    "loc": {
                      "start": {
                        "line": 52,
                        "column": 2
                      },
                      "end": {
                        "line": 58,
                        "column": 5
                      }
                    }
                  }
                ]
              },
              {
                "type": "ClassMethod",
                "start": 4321,
                "end": 4336,
                "loc": {
                  "start": {
                    "line": 59,
                    "column": 2
                  },
                  "end": {
                    "line": 60,
                    "column": 3
                  }
                },
                "computed": false,
                "key": {
                  "type": "Identifier",
                  "start": 4321,
                  "end": 4328,
                  "loc": {
                    "start": {
                      "line": 59,
                      "column": 2
                    },
                    "end": {
                      "line": 59,
                      "column": 9
                    },
                    "identifierName": "suspend"
                  },
                  "name": "suspend",
                  "leadingComments": null
                },
                "static": false,
                "kind": "method",
                "id": null,
                "generator": false,
                "expression": false,
                "async": false,
                "params": [],
                "body": {
                  "type": "BlockStatement",
                  "start": 4331,
                  "end": 4336,
                  "loc": {
                    "start": {
                      "line": 59,
                      "column": 12
                    },
                    "end": {
                      "line": 60,
                      "column": 3
                    }
                  },
                  "body": [],
                  "directives": []
                },
                "leadingComments": [
                  {
                    "type": "CommentBlock",
                    "value": "*\n   * Suspends the invocation of block objects on a dispatch object.\n   * @access public\n   * @returns {void}\n   * @desc By suspending a dispatch object, your application can temporarily prevent the execution of any blocks associated with that object. The suspension occurs after completion of any blocks running at the time of the call. Calling this function increments the suspension count of the object, and calling resume() decrements it. While the count is greater than zero, the object remains suspended, so you must balance each suspend() call with a matching resume() call.Any blocks submitted to a dispatch queue or events observed by a dispatch source are delivered once the object is resumed. \n   * @see https://developer.apple.com/reference/dispatch/dispatchobject/1452801-suspend\n   ",
                    "start": 3517,
                    "end": 4318,
                    "loc": {
                      "start": {
                        "line": 52,
                        "column": 2
                      },
                      "end": {
                        "line": 58,
                        "column": 5
                      }
                    }
                  }
                ]
              }
            ]
          },
          "leadingComments": [
            {
              "type": "CommentBlock",
              "value": "*\n * DispatchObject is the base class for many dispatch types, including DispatchQueue, DispatchGroup, and DispatchSource. \n * @access public\n * @see https://developer.apple.com/reference/dispatch/dispatchobject\n ",
              "start": 14,
              "end": 231,
              "loc": {
                "start": {
                  "line": 3,
                  "column": 0
                },
                "end": {
                  "line": 7,
                  "column": 3
                }
              }
            }
          ],
          "trailingComments": []
        },
        "leadingComments": [
          {
            "type": "CommentBlock",
            "value": "*\n * DispatchObject is the base class for many dispatch types, including DispatchQueue, DispatchGroup, and DispatchSource. \n * @access public\n * @see https://developer.apple.com/reference/dispatch/dispatchobject\n ",
            "start": 14,
            "end": 231,
            "loc": {
              "start": {
                "line": 3,
                "column": 0
              },
              "end": {
                "line": 7,
                "column": 3
              }
            }
          }
        ]
      }
    ],
    "directives": [
      {
        "type": "Directive",
        "start": 0,
        "end": 12,
        "loc": {
          "start": {
            "line": 1,
            "column": 0
          },
          "end": {
            "line": 1,
            "column": 12
          }
        },
        "value": {
          "type": "DirectiveLiteral",
          "start": 0,
          "end": 12,
          "loc": {
            "start": {
              "line": 1,
              "column": 0
            },
            "end": {
              "line": 1,
              "column": 12
            }
          },
          "value": "use strict",
          "extra": {
            "raw": "'use strict'",
            "rawValue": "use strict"
          },
          "trailingComments": null
        },
        "trailingComments": [
          {
            "type": "CommentBlock",
            "value": "*\n * DispatchObject is the base class for many dispatch types, including DispatchQueue, DispatchGroup, and DispatchSource. \n * @access public\n * @see https://developer.apple.com/reference/dispatch/dispatchobject\n ",
            "start": 14,
            "end": 231,
            "loc": {
              "start": {
                "line": 3,
                "column": 0
              },
              "end": {
                "line": 7,
                "column": 3
              }
            }
          }
        ]
      }
    ]
  },
  "comments": [
    {
      "type": "CommentBlock",
      "value": "*\n * DispatchObject is the base class for many dispatch types, including DispatchQueue, DispatchGroup, and DispatchSource. \n * @access public\n * @see https://developer.apple.com/reference/dispatch/dispatchobject\n ",
      "start": 14,
      "end": 231,
      "loc": {
        "start": {
          "line": 3,
          "column": 0
        },
        "end": {
          "line": 7,
          "column": 3
        }
      }
    },
    {
      "type": "CommentBlock",
      "value": "*\n   * constructor\n   * @access public\n   * @constructor\n   ",
      "start": 273,
      "end": 337,
      "loc": {
        "start": {
          "line": 10,
          "column": 2
        },
        "end": {
          "line": 14,
          "column": 5
        }
      }
    },
    {
      "type": "CommentLine",
      "value": " nothing to do",
      "start": 360,
      "end": 376,
      "loc": {
        "start": {
          "line": 16,
          "column": 4
        },
        "end": {
          "line": 16,
          "column": 20
        }
      }
    },
    {
      "type": "CommentLine",
      "value": " Instance Methods",
      "start": 384,
      "end": 403,
      "loc": {
        "start": {
          "line": 19,
          "column": 2
        },
        "end": {
          "line": 19,
          "column": 21
        }
      }
    },
    {
      "type": "CommentBlock",
      "value": "*\n   * Activates the dispatch object.\n   * @access public\n   * @returns {void}\n   * @desc Once a dispatch object has been activated, it cannot change its target queue.\n   * @see https://developer.apple.com/reference/dispatch/dispatchobject/1641002-activate\n   ",
      "start": 407,
      "end": 671,
      "loc": {
        "start": {
          "line": 21,
          "column": 2
        },
        "end": {
          "line": 27,
          "column": 5
        }
      }
    },
    {
      "type": "CommentBlock",
      "value": "*\n   * Resume the invocation of block objects on a dispatch object.\n   * @access public\n   * @returns {void}\n   * @desc Calling this function decrements the suspension count of a suspended dispatch queue or dispatch event source object. While the count is greater than zero, the object remains suspended. When the suspension count returns to zero, any blocks submitted to the dispatch queue or any events observed by the dispatch source while suspended are delivered.With one exception, each call to resume() must balance a call to suspend(). New dispatch event source objects returned by dispatch_source_create(_:_:_:_:) have a suspension count of 1 and must be resumed before any events are delivered. This approach allows your application to fully configure the dispatch event source object prior to delivery of the first event. In all other cases, it is undefined to call resume() more times than suspend(), which would result in a negative suspension count.\n   * @see https://developer.apple.com/reference/dispatch/dispatchobject/1452929-resume\n   ",
      "start": 694,
      "end": 1751,
      "loc": {
        "start": {
          "line": 31,
          "column": 2
        },
        "end": {
          "line": 37,
          "column": 5
        }
      }
    },
    {
      "type": "CommentBlock",
      "value": "*\n   * Sets the target queue for the given object.\n   * @access public\n   * @param {?DispatchQueue} queue - The new target queue for the object. The queue is retained, and the previous one, if any, is released. This parameter cannot be NULL.\n   * @returns {void}\n   * @desc An object's target queue is responsible for processing the object. The target queue determines the queue on which the object's finalizer is invoked. In addition, modifying the target queue of some objects changes their behavior:Dispatch queues:A dispatch queue's priority is inherited from its target queue. Use the dispatch_get_global_queue(_:_:) function to obtain a suitable target queue of the desired priority.If you submit a block to a serial queue, and the serial queue’s target queue is a different serial queue, that block is not invoked concurrently with blocks submitted to the target queue or to any other queue with that same target queue.ImportantIf you modify the target queue for a queue, you must be careful to avoid creating cycles in the queue hierarchy.Dispatch sources:A dispatch source's target queue specifies where its event handler and cancellation handler blocks are submitted.Dispatch I/O channels:A dispatch I/O channel's target queue specifies where its I/O operations are executed. This may affect the priority of the resulting I/O operations. For example, if the channel's target queue's priority is set to DISPATCH_QUEUE_PRIORITY_BACKGROUND, then any I/O operations performed by read(offset:length:queue:ioHandler:) or write(offset:data:queue:ioHandler:) on that queue are throttled when there is I/O contention.\n   * @see https://developer.apple.com/reference/dispatch/dispatchobject/1452989-settarget\n   ",
      "start": 1772,
      "end": 3488,
      "loc": {
        "start": {
          "line": 41,
          "column": 2
        },
        "end": {
          "line": 48,
          "column": 5
        }
      }
    },
    {
      "type": "CommentBlock",
      "value": "*\n   * Suspends the invocation of block objects on a dispatch object.\n   * @access public\n   * @returns {void}\n   * @desc By suspending a dispatch object, your application can temporarily prevent the execution of any blocks associated with that object. The suspension occurs after completion of any blocks running at the time of the call. Calling this function increments the suspension count of the object, and calling resume() decrements it. While the count is greater than zero, the object remains suspended, so you must balance each suspend() call with a matching resume() call.Any blocks submitted to a dispatch queue or events observed by a dispatch source are delivered once the object is resumed. \n   * @see https://developer.apple.com/reference/dispatch/dispatchobject/1452801-suspend\n   ",
      "start": 3517,
      "end": 4318,
      "loc": {
        "start": {
          "line": 52,
          "column": 2
        },
        "end": {
          "line": 58,
          "column": 5
        }
      }
    }
  ],
  "tokens": [
    {
      "type": {
        "label": "string",
        "beforeExpr": false,
        "startsExpr": true,
        "rightAssociative": false,
        "isLoop": false,
        "isAssign": false,
        "prefix": false,
        "postfix": false,
        "binop": null,
        "updateContext": null
      },
      "value": "use strict",
      "start": 0,
      "end": 12,
      "loc": {
        "start": {
          "line": 1,
          "column": 0
        },
        "end": {
          "line": 1,
          "column": 12
        }
      }
    },
    {
      "type": "CommentBlock",
      "value": "*\n * DispatchObject is the base class for many dispatch types, including DispatchQueue, DispatchGroup, and DispatchSource. \n * @access public\n * @see https://developer.apple.com/reference/dispatch/dispatchobject\n ",
      "start": 14,
      "end": 231,
      "loc": {
        "start": {
          "line": 3,
          "column": 0
        },
        "end": {
          "line": 7,
          "column": 3
        }
      }
    },
    {
      "type": {
        "label": "export",
        "keyword": "export",
        "beforeExpr": false,
        "startsExpr": false,
        "rightAssociative": false,
        "isLoop": false,
        "isAssign": false,
        "prefix": false,
        "postfix": false,
        "binop": null,
        "updateContext": null
      },
      "value": "export",
      "start": 232,
      "end": 238,
      "loc": {
        "start": {
          "line": 8,
          "column": 0
        },
        "end": {
          "line": 8,
          "column": 6
        }
      }
    },
    {
      "type": {
        "label": "default",
        "keyword": "default",
        "beforeExpr": true,
        "startsExpr": false,
        "rightAssociative": false,
        "isLoop": false,
        "isAssign": false,
        "prefix": false,
        "postfix": false,
        "binop": null,
        "updateContext": null
      },
      "value": "default",
      "start": 239,
      "end": 246,
      "loc": {
        "start": {
          "line": 8,
          "column": 7
        },
        "end": {
          "line": 8,
          "column": 14
        }
      }
    },
    {
      "type": {
        "label": "class",
        "keyword": "class",
        "beforeExpr": false,
        "startsExpr": false,
        "rightAssociative": false,
        "isLoop": false,
        "isAssign": false,
        "prefix": false,
        "postfix": false,
        "binop": null,
        "updateContext": null
      },
      "value": "class",
      "start": 247,
      "end": 252,
      "loc": {
        "start": {
          "line": 8,
          "column": 15
        },
        "end": {
          "line": 8,
          "column": 20
        }
      }
    },
    {
      "type": {
        "label": "name",
        "beforeExpr": false,
        "startsExpr": true,
        "rightAssociative": false,
        "isLoop": false,
        "isAssign": false,
        "prefix": false,
        "postfix": false,
        "binop": null
      },
      "value": "DispatchObject",
      "start": 253,
      "end": 267,
      "loc": {
        "start": {
          "line": 8,
          "column": 21
        },
        "end": {
          "line": 8,
          "column": 35
        }
      }
    },
    {
      "type": {
        "label": "{",
        "beforeExpr": true,
        "startsExpr": true,
        "rightAssociative": false,
        "isLoop": false,
        "isAssign": false,
        "prefix": false,
        "postfix": false,
        "binop": null
      },
      "start": 268,
      "end": 269,
      "loc": {
        "start": {
          "line": 8,
          "column": 36
        },
        "end": {
          "line": 8,
          "column": 37
        }
      }
    },
    {
      "type": "CommentBlock",
      "value": "*\n   * constructor\n   * @access public\n   * @constructor\n   ",
      "start": 273,
      "end": 337,
      "loc": {
        "start": {
          "line": 10,
          "column": 2
        },
        "end": {
          "line": 14,
          "column": 5
        }
      }
    },
    {
      "type": {
        "label": "name",
        "beforeExpr": false,
        "startsExpr": true,
        "rightAssociative": false,
        "isLoop": false,
        "isAssign": false,
        "prefix": false,
        "postfix": false,
        "binop": null
      },
      "value": "constructor",
      "start": 340,
      "end": 351,
      "loc": {
        "start": {
          "line": 15,
          "column": 2
        },
        "end": {
          "line": 15,
          "column": 13
        }
      }
    },
    {
      "type": {
        "label": "(",
        "beforeExpr": true,
        "startsExpr": true,
        "rightAssociative": false,
        "isLoop": false,
        "isAssign": false,
        "prefix": false,
        "postfix": false,
        "binop": null
      },
      "start": 351,
      "end": 352,
      "loc": {
        "start": {
          "line": 15,
          "column": 13
        },
        "end": {
          "line": 15,
          "column": 14
        }
      }
    },
    {
      "type": {
        "label": ")",
        "beforeExpr": false,
        "startsExpr": false,
        "rightAssociative": false,
        "isLoop": false,
        "isAssign": false,
        "prefix": false,
        "postfix": false,
        "binop": null
      },
      "start": 352,
      "end": 353,
      "loc": {
        "start": {
          "line": 15,
          "column": 14
        },
        "end": {
          "line": 15,
          "column": 15
        }
      }
    },
    {
      "type": {
        "label": "{",
        "beforeExpr": true,
        "startsExpr": true,
        "rightAssociative": false,
        "isLoop": false,
        "isAssign": false,
        "prefix": false,
        "postfix": false,
        "binop": null
      },
      "start": 354,
      "end": 355,
      "loc": {
        "start": {
          "line": 15,
          "column": 16
        },
        "end": {
          "line": 15,
          "column": 17
        }
      }
    },
    {
      "type": "CommentLine",
      "value": " nothing to do",
      "start": 360,
      "end": 376,
      "loc": {
        "start": {
          "line": 16,
          "column": 4
        },
        "end": {
          "line": 16,
          "column": 20
        }
      }
    },
    {
      "type": {
        "label": "}",
        "beforeExpr": false,
        "startsExpr": false,
        "rightAssociative": false,
        "isLoop": false,
        "isAssign": false,
        "prefix": false,
        "postfix": false,
        "binop": null
      },
      "start": 379,
      "end": 380,
      "loc": {
        "start": {
          "line": 17,
          "column": 2
        },
        "end": {
          "line": 17,
          "column": 3
        }
      }
    },
    {
      "type": "CommentLine",
      "value": " Instance Methods",
      "start": 384,
      "end": 403,
      "loc": {
        "start": {
          "line": 19,
          "column": 2
        },
        "end": {
          "line": 19,
          "column": 21
        }
      }
    },
    {
      "type": "CommentBlock",
      "value": "*\n   * Activates the dispatch object.\n   * @access public\n   * @returns {void}\n   * @desc Once a dispatch object has been activated, it cannot change its target queue.\n   * @see https://developer.apple.com/reference/dispatch/dispatchobject/1641002-activate\n   ",
      "start": 407,
      "end": 671,
      "loc": {
        "start": {
          "line": 21,
          "column": 2
        },
        "end": {
          "line": 27,
          "column": 5
        }
      }
    },
    {
      "type": {
        "label": "name",
        "beforeExpr": false,
        "startsExpr": true,
        "rightAssociative": false,
        "isLoop": false,
        "isAssign": false,
        "prefix": false,
        "postfix": false,
        "binop": null
      },
      "value": "activate",
      "start": 674,
      "end": 682,
      "loc": {
        "start": {
          "line": 28,
          "column": 2
        },
        "end": {
          "line": 28,
          "column": 10
        }
      }
    },
    {
      "type": {
        "label": "(",
        "beforeExpr": true,
        "startsExpr": true,
        "rightAssociative": false,
        "isLoop": false,
        "isAssign": false,
        "prefix": false,
        "postfix": false,
        "binop": null
      },
      "start": 682,
      "end": 683,
      "loc": {
        "start": {
          "line": 28,
          "column": 10
        },
        "end": {
          "line": 28,
          "column": 11
        }
      }
    },
    {
      "type": {
        "label": ")",
        "beforeExpr": false,
        "startsExpr": false,
        "rightAssociative": false,
        "isLoop": false,
        "isAssign": false,
        "prefix": false,
        "postfix": false,
        "binop": null
      },
      "start": 683,
      "end": 684,
      "loc": {
        "start": {
          "line": 28,
          "column": 11
        },
        "end": {
          "line": 28,
          "column": 12
        }
      }
    },
    {
      "type": {
        "label": "{",
        "beforeExpr": true,
        "startsExpr": true,
        "rightAssociative": false,
        "isLoop": false,
        "isAssign": false,
        "prefix": false,
        "postfix": false,
        "binop": null
      },
      "start": 685,
      "end": 686,
      "loc": {
        "start": {
          "line": 28,
          "column": 13
        },
        "end": {
          "line": 28,
          "column": 14
        }
      }
    },
    {
      "type": {
        "label": "}",
        "beforeExpr": false,
        "startsExpr": false,
        "rightAssociative": false,
        "isLoop": false,
        "isAssign": false,
        "prefix": false,
        "postfix": false,
        "binop": null
      },
      "start": 689,
      "end": 690,
      "loc": {
        "start": {
          "line": 29,
          "column": 2
        },
        "end": {
          "line": 29,
          "column": 3
        }
      }
    },
    {
      "type": "CommentBlock",
      "value": "*\n   * Resume the invocation of block objects on a dispatch object.\n   * @access public\n   * @returns {void}\n   * @desc Calling this function decrements the suspension count of a suspended dispatch queue or dispatch event source object. While the count is greater than zero, the object remains suspended. When the suspension count returns to zero, any blocks submitted to the dispatch queue or any events observed by the dispatch source while suspended are delivered.With one exception, each call to resume() must balance a call to suspend(). New dispatch event source objects returned by dispatch_source_create(_:_:_:_:) have a suspension count of 1 and must be resumed before any events are delivered. This approach allows your application to fully configure the dispatch event source object prior to delivery of the first event. In all other cases, it is undefined to call resume() more times than suspend(), which would result in a negative suspension count.\n   * @see https://developer.apple.com/reference/dispatch/dispatchobject/1452929-resume\n   ",
      "start": 694,
      "end": 1751,
      "loc": {
        "start": {
          "line": 31,
          "column": 2
        },
        "end": {
          "line": 37,
          "column": 5
        }
      }
    },
    {
      "type": {
        "label": "name",
        "beforeExpr": false,
        "startsExpr": true,
        "rightAssociative": false,
        "isLoop": false,
        "isAssign": false,
        "prefix": false,
        "postfix": false,
        "binop": null
      },
      "value": "resume",
      "start": 1754,
      "end": 1760,
      "loc": {
        "start": {
          "line": 38,
          "column": 2
        },
        "end": {
          "line": 38,
          "column": 8
        }
      }
    },
    {
      "type": {
        "label": "(",
        "beforeExpr": true,
        "startsExpr": true,
        "rightAssociative": false,
        "isLoop": false,
        "isAssign": false,
        "prefix": false,
        "postfix": false,
        "binop": null
      },
      "start": 1760,
      "end": 1761,
      "loc": {
        "start": {
          "line": 38,
          "column": 8
        },
        "end": {
          "line": 38,
          "column": 9
        }
      }
    },
    {
      "type": {
        "label": ")",
        "beforeExpr": false,
        "startsExpr": false,
        "rightAssociative": false,
        "isLoop": false,
        "isAssign": false,
        "prefix": false,
        "postfix": false,
        "binop": null
      },
      "start": 1761,
      "end": 1762,
      "loc": {
        "start": {
          "line": 38,
          "column": 9
        },
        "end": {
          "line": 38,
          "column": 10
        }
      }
    },
    {
      "type": {
        "label": "{",
        "beforeExpr": true,
        "startsExpr": true,
        "rightAssociative": false,
        "isLoop": false,
        "isAssign": false,
        "prefix": false,
        "postfix": false,
        "binop": null
      },
      "start": 1763,
      "end": 1764,
      "loc": {
        "start": {
          "line": 38,
          "column": 11
        },
        "end": {
          "line": 38,
          "column": 12
        }
      }
    },
    {
      "type": {
        "label": "}",
        "beforeExpr": false,
        "startsExpr": false,
        "rightAssociative": false,
        "isLoop": false,
        "isAssign": false,
        "prefix": false,
        "postfix": false,
        "binop": null
      },
      "start": 1767,
      "end": 1768,
      "loc": {
        "start": {
          "line": 39,
          "column": 2
        },
        "end": {
          "line": 39,
          "column": 3
        }
      }
    },
    {
      "type": "CommentBlock",
      "value": "*\n   * Sets the target queue for the given object.\n   * @access public\n   * @param {?DispatchQueue} queue - The new target queue for the object. The queue is retained, and the previous one, if any, is released. This parameter cannot be NULL.\n   * @returns {void}\n   * @desc An object's target queue is responsible for processing the object. The target queue determines the queue on which the object's finalizer is invoked. In addition, modifying the target queue of some objects changes their behavior:Dispatch queues:A dispatch queue's priority is inherited from its target queue. Use the dispatch_get_global_queue(_:_:) function to obtain a suitable target queue of the desired priority.If you submit a block to a serial queue, and the serial queue’s target queue is a different serial queue, that block is not invoked concurrently with blocks submitted to the target queue or to any other queue with that same target queue.ImportantIf you modify the target queue for a queue, you must be careful to avoid creating cycles in the queue hierarchy.Dispatch sources:A dispatch source's target queue specifies where its event handler and cancellation handler blocks are submitted.Dispatch I/O channels:A dispatch I/O channel's target queue specifies where its I/O operations are executed. This may affect the priority of the resulting I/O operations. For example, if the channel's target queue's priority is set to DISPATCH_QUEUE_PRIORITY_BACKGROUND, then any I/O operations performed by read(offset:length:queue:ioHandler:) or write(offset:data:queue:ioHandler:) on that queue are throttled when there is I/O contention.\n   * @see https://developer.apple.com/reference/dispatch/dispatchobject/1452989-settarget\n   ",
      "start": 1772,
      "end": 3488,
      "loc": {
        "start": {
          "line": 41,
          "column": 2
        },
        "end": {
          "line": 48,
          "column": 5
        }
      }
    },
    {
      "type": {
        "label": "name",
        "beforeExpr": false,
        "startsExpr": true,
        "rightAssociative": false,
        "isLoop": false,
        "isAssign": false,
        "prefix": false,
        "postfix": false,
        "binop": null
      },
      "value": "setTarget",
      "start": 3491,
      "end": 3500,
      "loc": {
        "start": {
          "line": 49,
          "column": 2
        },
        "end": {
          "line": 49,
          "column": 11
        }
      }
    },
    {
      "type": {
        "label": "(",
        "beforeExpr": true,
        "startsExpr": true,
        "rightAssociative": false,
        "isLoop": false,
        "isAssign": false,
        "prefix": false,
        "postfix": false,
        "binop": null
      },
      "start": 3500,
      "end": 3501,
      "loc": {
        "start": {
          "line": 49,
          "column": 11
        },
        "end": {
          "line": 49,
          "column": 12
        }
      }
    },
    {
      "type": {
        "label": "name",
        "beforeExpr": false,
        "startsExpr": true,
        "rightAssociative": false,
        "isLoop": false,
        "isAssign": false,
        "prefix": false,
        "postfix": false,
        "binop": null
      },
      "value": "queue",
      "start": 3501,
      "end": 3506,
      "loc": {
        "start": {
          "line": 49,
          "column": 12
        },
        "end": {
          "line": 49,
          "column": 17
        }
      }
    },
    {
      "type": {
        "label": ")",
        "beforeExpr": false,
        "startsExpr": false,
        "rightAssociative": false,
        "isLoop": false,
        "isAssign": false,
        "prefix": false,
        "postfix": false,
        "binop": null
      },
      "start": 3506,
      "end": 3507,
      "loc": {
        "start": {
          "line": 49,
          "column": 17
        },
        "end": {
          "line": 49,
          "column": 18
        }
      }
    },
    {
      "type": {
        "label": "{",
        "beforeExpr": true,
        "startsExpr": true,
        "rightAssociative": false,
        "isLoop": false,
        "isAssign": false,
        "prefix": false,
        "postfix": false,
        "binop": null
      },
      "start": 3508,
      "end": 3509,
      "loc": {
        "start": {
          "line": 49,
          "column": 19
        },
        "end": {
          "line": 49,
          "column": 20
        }
      }
    },
    {
      "type": {
        "label": "}",
        "beforeExpr": false,
        "startsExpr": false,
        "rightAssociative": false,
        "isLoop": false,
        "isAssign": false,
        "prefix": false,
        "postfix": false,
        "binop": null
      },
      "start": 3512,
      "end": 3513,
      "loc": {
        "start": {
          "line": 50,
          "column": 2
        },
        "end": {
          "line": 50,
          "column": 3
        }
      }
    },
    {
      "type": "CommentBlock",
      "value": "*\n   * Suspends the invocation of block objects on a dispatch object.\n   * @access public\n   * @returns {void}\n   * @desc By suspending a dispatch object, your application can temporarily prevent the execution of any blocks associated with that object. The suspension occurs after completion of any blocks running at the time of the call. Calling this function increments the suspension count of the object, and calling resume() decrements it. While the count is greater than zero, the object remains suspended, so you must balance each suspend() call with a matching resume() call.Any blocks submitted to a dispatch queue or events observed by a dispatch source are delivered once the object is resumed. \n   * @see https://developer.apple.com/reference/dispatch/dispatchobject/1452801-suspend\n   ",
      "start": 3517,
      "end": 4318,
      "loc": {
        "start": {
          "line": 52,
          "column": 2
        },
        "end": {
          "line": 58,
          "column": 5
        }
      }
    },
    {
      "type": {
        "label": "name",
        "beforeExpr": false,
        "startsExpr": true,
        "rightAssociative": false,
        "isLoop": false,
        "isAssign": false,
        "prefix": false,
        "postfix": false,
        "binop": null
      },
      "value": "suspend",
      "start": 4321,
      "end": 4328,
      "loc": {
        "start": {
          "line": 59,
          "column": 2
        },
        "end": {
          "line": 59,
          "column": 9
        }
      }
    },
    {
      "type": {
        "label": "(",
        "beforeExpr": true,
        "startsExpr": true,
        "rightAssociative": false,
        "isLoop": false,
        "isAssign": false,
        "prefix": false,
        "postfix": false,
        "binop": null
      },
      "start": 4328,
      "end": 4329,
      "loc": {
        "start": {
          "line": 59,
          "column": 9
        },
        "end": {
          "line": 59,
          "column": 10
        }
      }
    },
    {
      "type": {
        "label": ")",
        "beforeExpr": false,
        "startsExpr": false,
        "rightAssociative": false,
        "isLoop": false,
        "isAssign": false,
        "prefix": false,
        "postfix": false,
        "binop": null
      },
      "start": 4329,
      "end": 4330,
      "loc": {
        "start": {
          "line": 59,
          "column": 10
        },
        "end": {
          "line": 59,
          "column": 11
        }
      }
    },
    {
      "type": {
        "label": "{",
        "beforeExpr": true,
        "startsExpr": true,
        "rightAssociative": false,
        "isLoop": false,
        "isAssign": false,
        "prefix": false,
        "postfix": false,
        "binop": null
      },
      "start": 4331,
      "end": 4332,
      "loc": {
        "start": {
          "line": 59,
          "column": 12
        },
        "end": {
          "line": 59,
          "column": 13
        }
      }
    },
    {
      "type": {
        "label": "}",
        "beforeExpr": false,
        "startsExpr": false,
        "rightAssociative": false,
        "isLoop": false,
        "isAssign": false,
        "prefix": false,
        "postfix": false,
        "binop": null
      },
      "start": 4335,
      "end": 4336,
      "loc": {
        "start": {
          "line": 60,
          "column": 2
        },
        "end": {
          "line": 60,
          "column": 3
        }
      }
    },
    {
      "type": {
        "label": "}",
        "beforeExpr": false,
        "startsExpr": false,
        "rightAssociative": false,
        "isLoop": false,
        "isAssign": false,
        "prefix": false,
        "postfix": false,
        "binop": null
      },
      "start": 4337,
      "end": 4338,
      "loc": {
        "start": {
          "line": 61,
          "column": 0
        },
        "end": {
          "line": 61,
          "column": 1
        }
      }
    },
    {
      "type": {
        "label": "eof",
        "beforeExpr": false,
        "startsExpr": false,
        "rightAssociative": false,
        "isLoop": false,
        "isAssign": false,
        "prefix": false,
        "postfix": false,
        "binop": null,
        "updateContext": null
      },
      "start": 4339,
      "end": 4339,
      "loc": {
        "start": {
          "line": 62,
          "column": 0
        },
        "end": {
          "line": 62,
          "column": 0
        }
      }
    }
  ]
}